[
    {
        "Channel_ID": "UC_-LsoQ-dQns_PFIZ89Wy-w",
        "Video_ID": "F_8KmyfAYBw",
        "View_Count": "55",
        "Published_At": "2024-02-26T06:52:26Z",
        "Video_Title": "Vision Recalibration | Neukalibrierung der Vision"
    },
    {
        "Channel_ID": "UC_-LsoQ-dQns_PFIZ89Wy-w",
        "Video_ID": "BmJ0zjToOTA",
        "View_Count": "65",
        "Published_At": "2024-02-18T20:23:20Z",
        "Video_Title": "Humble yourself | Dem\u00fctige dich selbst"
    },
    {
        "Channel_ID": "UC_-LsoQ-dQns_PFIZ89Wy-w",
        "Video_ID": "E40YiFfNeEM",
        "View_Count": "31",
        "Published_At": "2024-02-12T06:44:18Z",
        "Video_Title": "Stay faithful to God | Bleib Gott gegen\u00fcber treu"
    },
    {
        "Channel_ID": "UC_-LsoQ-dQns_PFIZ89Wy-w",
        "Video_ID": "Z9jLIOgMnCY",
        "View_Count": "56",
        "Published_At": "2024-02-05T06:43:24Z",
        "Video_Title": "Through difficulties and problems | Durch Herausforderungen und Probleme"
    },
    {
        "Channel_ID": "UC_-LsoQ-dQns_PFIZ89Wy-w",
        "Video_ID": "GwcbQ4Pgmpc",
        "View_Count": "37",
        "Published_At": "2024-01-29T06:31:14Z",
        "Video_Title": "God's creative power in you | Gottes sch\u00f6pferische Kraft in dir"
    },
    {
        "Channel_ID": "UC_-LsoQ-dQns_PFIZ89Wy-w",
        "Video_ID": "2ewgYp8tGc0",
        "View_Count": "52",
        "Published_At": "2024-01-15T06:24:15Z",
        "Video_Title": "Program yourself by the Word Part 2 | Programmiere dich durch das Wort Teil 2"
    },
    {
        "Channel_ID": "UC_-LsoQ-dQns_PFIZ89Wy-w",
        "Video_ID": "bry1jp1oD7Y",
        "View_Count": "50",
        "Published_At": "2024-01-08T06:32:04Z",
        "Video_Title": "Program yourself by the Word | Programmiere dich durch das Wort"
    },
    {
        "Channel_ID": "UC_-LsoQ-dQns_PFIZ89Wy-w",
        "Video_ID": "qZIBK-3PJOs",
        "View_Count": "71",
        "Published_At": "2024-01-01T11:22:32Z",
        "Video_Title": "New Year Eve Church Service 2023 | Silvester Gottesdienst 2023"
    },
    {
        "Channel_ID": "UC_-LsoQ-dQns_PFIZ89Wy-w",
        "Video_ID": "Kj9jjEXHjYk",
        "View_Count": "37",
        "Published_At": "2023-12-18T06:33:18Z",
        "Video_Title": "Who is this child? Part 2 | Wer ist dieses Kind? Teil 2"
    },
    {
        "Channel_ID": "UC_-LsoQ-dQns_PFIZ89Wy-w",
        "Video_ID": "D9mVIyw_Qy4",
        "View_Count": "43",
        "Published_At": "2023-12-11T06:55:46Z",
        "Video_Title": "Who is this child? | Wer ist dieses Kind?"
    },
    {
        "Channel_ID": "UC_-LsoQ-dQns_PFIZ89Wy-w",
        "Video_ID": "JjK8KJbEr2g",
        "View_Count": "42",
        "Published_At": "2023-12-04T06:38:44Z",
        "Video_Title": "Kenosis"
    },
    {
        "Channel_ID": "UC_-LsoQ-dQns_PFIZ89Wy-w",
        "Video_ID": "L4fa_lOAtHY",
        "View_Count": "89",
        "Published_At": "2023-11-26T18:17:50Z",
        "Video_Title": "What are you taking with you in your boat? | Was nimmst du in deinem Boot mit?"
    },
    {
        "Channel_ID": "UC_-LsoQ-dQns_PFIZ89Wy-w",
        "Video_ID": "2Moqib8WFj4",
        "View_Count": "74",
        "Published_At": "2023-11-20T06:11:12Z",
        "Video_Title": "Living by faith | Leben im Glauben"
    },
    {
        "Channel_ID": "UC_-LsoQ-dQns_PFIZ89Wy-w",
        "Video_ID": "5NafD4GI-Wc",
        "View_Count": "66",
        "Published_At": "2023-11-13T06:17:38Z",
        "Video_Title": "Renewing the mind | Erneuerung des Sinnes"
    },
    {
        "Channel_ID": "UC_-LsoQ-dQns_PFIZ89Wy-w",
        "Video_ID": "BH-XjBXIAX0",
        "View_Count": "42",
        "Published_At": "2023-11-06T06:00:14Z",
        "Video_Title": "The power of a grateful heart | Die Macht eines dankbaren Herzens"
    },
    {
        "Channel_ID": "UC_-LsoQ-dQns_PFIZ89Wy-w",
        "Video_ID": "_s3NQJ6Xkf4",
        "View_Count": "66",
        "Published_At": "2023-10-30T06:38:14Z",
        "Video_Title": "Give your fear to Jesus | Gib deine \u00c4ngste zu Jesus"
    },
    {
        "Channel_ID": "UC_-LsoQ-dQns_PFIZ89Wy-w",
        "Video_ID": "D_B0WdbGy00",
        "View_Count": "65",
        "Published_At": "2023-10-23T05:32:34Z",
        "Video_Title": "Planned and Planted by God | Von Gott geplant und gepflanzt"
    },
    {
        "Channel_ID": "UC_-LsoQ-dQns_PFIZ89Wy-w",
        "Video_ID": "7Zmk-BSsmaE",
        "View_Count": "35",
        "Published_At": "2023-10-16T05:14:50Z",
        "Video_Title": "Victory in Christ Part 2  | Sieg in Christus Teil 2"
    },
    {
        "Channel_ID": "UC_-LsoQ-dQns_PFIZ89Wy-w",
        "Video_ID": "Zb9U_gTJtR8",
        "View_Count": "47",
        "Published_At": "2023-10-09T05:19:20Z",
        "Video_Title": "Victory in Christ | Sieg in Christus"
    },
    {
        "Channel_ID": "UC_-LsoQ-dQns_PFIZ89Wy-w",
        "Video_ID": "hgyCxJZDEZQ",
        "View_Count": "35",
        "Published_At": "2023-10-02T05:39:49Z",
        "Video_Title": "Taste it Part 3 | Probier es Teil 3"
    },
    {
        "Channel_ID": "UC_-LsoQ-dQns_PFIZ89Wy-w",
        "Video_ID": "6eFBdF5LHac",
        "View_Count": "47",
        "Published_At": "2023-09-25T05:47:24Z",
        "Video_Title": "Treue und Loyalit\u00e4t | Faithfulness and Loyalty"
    },
    {
        "Channel_ID": "UC_-LsoQ-dQns_PFIZ89Wy-w",
        "Video_ID": "IyDNHX-3UQs",
        "View_Count": "55",
        "Published_At": "2023-09-18T05:17:32Z",
        "Video_Title": "Taste it Part 2 | Probier es Teil 2"
    },
    {
        "Channel_ID": "UC_-LsoQ-dQns_PFIZ89Wy-w",
        "Video_ID": "uSYF1cIuge8",
        "View_Count": "76",
        "Published_At": "2023-09-17T08:55:20Z",
        "Video_Title": "Taste it | Probier es"
    },
    {
        "Channel_ID": "UC_-LsoQ-dQns_PFIZ89Wy-w",
        "Video_ID": "tPPZVpngV5Q",
        "View_Count": "97",
        "Published_At": "2023-09-04T05:09:26Z",
        "Video_Title": "Walking in love Part 5 | In Liebe wandeln Teil 5"
    },
    {
        "Channel_ID": "UC_-LsoQ-dQns_PFIZ89Wy-w",
        "Video_ID": "vcZMhtjjxn0",
        "View_Count": "78",
        "Published_At": "2023-08-28T05:35:35Z",
        "Video_Title": "Walking in love Part 4 | In Liebe wandeln Teil 4"
    },
    {
        "Channel_ID": "UC_-LsoQ-dQns_PFIZ89Wy-w",
        "Video_ID": "1NB2WWvLmZk",
        "View_Count": "105",
        "Published_At": "2023-08-14T05:40:27Z",
        "Video_Title": "Walking in love Part 3 | In Liebe wandeln Teil 3"
    },
    {
        "Channel_ID": "UC_-LsoQ-dQns_PFIZ89Wy-w",
        "Video_ID": "WJXe3PJ-uUQ",
        "View_Count": "79",
        "Published_At": "2023-08-07T05:03:43Z",
        "Video_Title": "Satan the mind manipulator | Satan der Gedankenmanipulator"
    },
    {
        "Channel_ID": "UC_-LsoQ-dQns_PFIZ89Wy-w",
        "Video_ID": "EHi2VASgRy8",
        "View_Count": "86",
        "Published_At": "2023-07-31T05:47:23Z",
        "Video_Title": "Walking in Love Part 2 | In Liebe wandeln Teil 2"
    },
    {
        "Channel_ID": "UC_-LsoQ-dQns_PFIZ89Wy-w",
        "Video_ID": "8_wa9fNyCCw",
        "View_Count": "115",
        "Published_At": "2023-07-24T05:33:35Z",
        "Video_Title": "Walking in Love | In Liebe wandeln"
    },
    {
        "Channel_ID": "UC_-LsoQ-dQns_PFIZ89Wy-w",
        "Video_ID": "gPHMYwmoK7Q",
        "View_Count": "60",
        "Published_At": "2023-07-17T05:29:51Z",
        "Video_Title": "I am Andrew Part 2 | Ich bin Andreas Teil 2"
    },
    {
        "Channel_ID": "UC_-LsoQ-dQns_PFIZ89Wy-w",
        "Video_ID": "7pLyTZi6x50",
        "View_Count": "81",
        "Published_At": "2023-07-10T05:23:03Z",
        "Video_Title": "I am Andrew Part 1 | Ich bin Andreas Teil 1"
    },
    {
        "Channel_ID": "UC_-LsoQ-dQns_PFIZ89Wy-w",
        "Video_ID": "qesg1erY-gk",
        "View_Count": "40",
        "Published_At": "2023-06-26T06:39:53Z",
        "Video_Title": "Humbleness and obedience vs. sacrifice Part 2 | Demut und Gehorsam vs. Aufopferung"
    },
    {
        "Channel_ID": "UC_-LsoQ-dQns_PFIZ89Wy-w",
        "Video_ID": "G0EXjkmWKJk",
        "View_Count": "71",
        "Published_At": "2023-06-19T08:29:13Z",
        "Video_Title": "Don't limit God in you | Limitiere Gott nicht in dir"
    },
    {
        "Channel_ID": "UC_-LsoQ-dQns_PFIZ89Wy-w",
        "Video_ID": "8ji4XTQXWMM",
        "View_Count": "50",
        "Published_At": "2023-06-12T06:11:22Z",
        "Video_Title": "Humbleness and obedience vs. sacrifice | Demut und Gehorsam vs. Aufopferung"
    },
    {
        "Channel_ID": "UC_-LsoQ-dQns_PFIZ89Wy-w",
        "Video_ID": "_c4lz4_olBg",
        "View_Count": "51",
        "Published_At": "2023-06-05T05:22:14Z",
        "Video_Title": "Living with an eternal mentality | Leben mit einem Geist der Ewigkeit"
    },
    {
        "Channel_ID": "UC_-LsoQ-dQns_PFIZ89Wy-w",
        "Video_ID": "K6Bp0ik_Nmc",
        "View_Count": "65",
        "Published_At": "2023-05-29T06:02:51Z",
        "Video_Title": "The indwelling presence of the holy spirit | Die innewohnende Gegenwart des Heiligen Geistes"
    },
    {
        "Channel_ID": "UC_-LsoQ-dQns_PFIZ89Wy-w",
        "Video_ID": "vMTzCadmXa4",
        "View_Count": "97",
        "Published_At": "2023-03-05T19:00:31Z",
        "Video_Title": "City Light Workshop Part 1"
    },
    {
        "Channel_ID": "UC_-LsoQ-dQns_PFIZ89Wy-w",
        "Video_ID": "wngCDvpPRnY",
        "View_Count": "39",
        "Published_At": "2023-03-05T19:00:25Z",
        "Video_Title": "City Light Workshop Part2"
    },
    {
        "Channel_ID": "UC_-LsoQ-dQns_PFIZ89Wy-w",
        "Video_ID": "Btq1VOSIpgU",
        "View_Count": "29",
        "Published_At": "2023-03-05T19:00:06Z",
        "Video_Title": "City Light Workshop Part 3"
    },
    {
        "Channel_ID": "UC_-LsoQ-dQns_PFIZ89Wy-w",
        "Video_ID": "6JiYVuta4yA",
        "View_Count": "104",
        "Published_At": "2023-02-19T16:55:11Z",
        "Video_Title": "Gott ist ein Zufluchtsort. | God is a shelter."
    },
    {
        "Channel_ID": "UC_-LsoQ-dQns_PFIZ89Wy-w",
        "Video_ID": "3mWSkFUl0zA",
        "View_Count": "76",
        "Published_At": "2022-12-31T07:00:02Z",
        "Video_Title": "Happy new Year | Frohes neues Jahr"
    },
    {
        "Channel_ID": "UC_-LsoQ-dQns_PFIZ89Wy-w",
        "Video_ID": "_oVHfEXShJQ",
        "View_Count": "91",
        "Published_At": "2022-12-18T18:08:24Z",
        "Video_Title": "What kind of people? | Welche Art von Menschen?"
    },
    {
        "Channel_ID": "UC_-LsoQ-dQns_PFIZ89Wy-w",
        "Video_ID": "wJsEsEJib0Q",
        "View_Count": "58",
        "Published_At": "2022-11-27T23:06:35Z",
        "Video_Title": "Rescue Mission | Rettungsmission"
    },
    {
        "Channel_ID": "UC_-LsoQ-dQns_PFIZ89Wy-w",
        "Video_ID": "kwRd00MJyf0",
        "View_Count": "56",
        "Published_At": "2022-11-20T22:56:54Z",
        "Video_Title": "Sprich es aus und erz\u00e4hle es anderen | Speak out and tell others"
    },
    {
        "Channel_ID": "UC_-LsoQ-dQns_PFIZ89Wy-w",
        "Video_ID": "eXSJc_xR-Ag",
        "View_Count": "41",
        "Published_At": "2022-11-13T22:51:20Z",
        "Video_Title": "Ich habe Mut | I have confidence"
    },
    {
        "Channel_ID": "UC_-LsoQ-dQns_PFIZ89Wy-w",
        "Video_ID": "mrsCjmd9F38",
        "View_Count": "76",
        "Published_At": "2022-11-13T15:06:41Z",
        "Video_Title": "Ank\u00fcndigung | Announcement"
    },
    {
        "Channel_ID": "UC_-LsoQ-dQns_PFIZ89Wy-w",
        "Video_ID": "sDNPuXyJDGo",
        "View_Count": "35",
        "Published_At": "2022-11-06T22:59:56Z",
        "Video_Title": "Mir mangelt es an nichts Part 2 | I lack nothing Part 2"
    },
    {
        "Channel_ID": "UC_-LsoQ-dQns_PFIZ89Wy-w",
        "Video_ID": "Xx4K2bJJQ7g",
        "View_Count": "45",
        "Published_At": "2022-10-30T22:46:10Z",
        "Video_Title": "Mir mangelt es an nichts | I lack nothing"
    },
    {
        "Channel_ID": "UC_-LsoQ-dQns_PFIZ89Wy-w",
        "Video_ID": "HEaqN0dRpdA",
        "View_Count": "62",
        "Published_At": "2022-10-23T22:05:35Z",
        "Video_Title": "Social out reach through \"city light\" | Soziale Reichweite durch \"city light\""
    },
    {
        "Channel_ID": "UC_-LsoQ-dQns_PFIZ89Wy-w",
        "Video_ID": "Ch2SEZT9cxo",
        "View_Count": "68",
        "Published_At": "2022-10-16T21:53:24Z",
        "Video_Title": "Life anchor | Lebensanker"
    },
    {
        "Channel_ID": "UC_-LsoQ-dQns_PFIZ89Wy-w",
        "Video_ID": "68yxHgFXW6A",
        "View_Count": "53",
        "Published_At": "2022-10-09T21:54:33Z",
        "Video_Title": "Worship GOD | Bete GOTT an"
    },
    {
        "Channel_ID": "UC_-LsoQ-dQns_PFIZ89Wy-w",
        "Video_ID": "O3ZJg5bhEZM",
        "View_Count": "76",
        "Published_At": "2022-10-02T22:09:38Z",
        "Video_Title": "What are you looking at? | Worauf schaust du?"
    },
    {
        "Channel_ID": "UC_-LsoQ-dQns_PFIZ89Wy-w",
        "Video_ID": "heikra8LfUg",
        "View_Count": "62",
        "Published_At": "2022-09-25T21:50:33Z",
        "Video_Title": "Einige M\u00f6glichkeiten, auf Herausforderungen zu reagieren 4 | Some ways to respond in challenges 4"
    },
    {
        "Channel_ID": "UC_-LsoQ-dQns_PFIZ89Wy-w",
        "Video_ID": "GHvmNpALirc",
        "View_Count": "65",
        "Published_At": "2022-09-18T21:57:41Z",
        "Video_Title": "Einige M\u00f6glichkeiten, auf Herausforderungen zu reagieren 3 | Some ways to respond in challenges 3"
    },
    {
        "Channel_ID": "UC_-LsoQ-dQns_PFIZ89Wy-w",
        "Video_ID": "3Sr0OebEqRs",
        "View_Count": "71",
        "Published_At": "2022-09-11T21:53:36Z",
        "Video_Title": "Einige M\u00f6glichkeiten, auf Herausforderungen zu reagieren 2 | Some ways to respond in challenges 2"
    },
    {
        "Channel_ID": "UC_-LsoQ-dQns_PFIZ89Wy-w",
        "Video_ID": "UcL0jM7lfHk",
        "View_Count": "103",
        "Published_At": "2022-09-04T22:06:08Z",
        "Video_Title": "Einige M\u00f6glichkeiten, auf Herausforderungen zu reagieren | Some ways to respond in challenges"
    },
    {
        "Channel_ID": "UC_-LsoQ-dQns_PFIZ89Wy-w",
        "Video_ID": "G1FwmkXk1ws",
        "View_Count": "77",
        "Published_At": "2022-08-21T22:34:05Z",
        "Video_Title": "Planned by God | Von Gott geplant"
    },
    {
        "Channel_ID": "UC_-LsoQ-dQns_PFIZ89Wy-w",
        "Video_ID": "BUrWm3o2QiY",
        "View_Count": "79",
        "Published_At": "2022-08-14T21:56:12Z",
        "Video_Title": "Worship GOD | Bete GOTT an"
    },
    {
        "Channel_ID": "UC_-LsoQ-dQns_PFIZ89Wy-w",
        "Video_ID": "kqDuCFu27Vw",
        "View_Count": "73",
        "Published_At": "2022-08-07T22:23:19Z",
        "Video_Title": "Joy | Freude"
    },
    {
        "Channel_ID": "UC_-LsoQ-dQns_PFIZ89Wy-w",
        "Video_ID": "aobztxGV-LY",
        "View_Count": "85",
        "Published_At": "2022-07-31T22:35:19Z",
        "Video_Title": "Water Baptism | Wassertaufe"
    },
    {
        "Channel_ID": "UC_-LsoQ-dQns_PFIZ89Wy-w",
        "Video_ID": "RVpwqdGcPKE",
        "View_Count": "130",
        "Published_At": "2022-07-24T22:33:30Z",
        "Video_Title": "In what state is your thought? | In Welchem Zustand sind deine Gedanken?"
    },
    {
        "Channel_ID": "UC_-LsoQ-dQns_PFIZ89Wy-w",
        "Video_ID": "Um0B4khLgxQ",
        "View_Count": "81",
        "Published_At": "2022-07-17T22:42:11Z",
        "Video_Title": "Worry is unbelief Part 4 | Sorge ist Unglaube Teil 4"
    },
    {
        "Channel_ID": "UC_-LsoQ-dQns_PFIZ89Wy-w",
        "Video_ID": "PWCXdIz00OQ",
        "View_Count": "68",
        "Published_At": "2022-07-10T22:53:50Z",
        "Video_Title": "Worry is unbelief Part 3 | Sorge ist Unglaube Teil 3"
    },
    {
        "Channel_ID": "UC_-LsoQ-dQns_PFIZ89Wy-w",
        "Video_ID": "GjpI58-AmKs",
        "View_Count": "120",
        "Published_At": "2022-07-03T22:35:49Z",
        "Video_Title": "Der Heilige Geist braucht dich egal wie alt du bist"
    },
    {
        "Channel_ID": "UC_-LsoQ-dQns_PFIZ89Wy-w",
        "Video_ID": "GSHLz0c-Kks",
        "View_Count": "94",
        "Published_At": "2022-06-26T22:37:17Z",
        "Video_Title": "Worry is unbelief Part 2 | Sorge ist Unglaube Teil 2"
    },
    {
        "Channel_ID": "UC_-LsoQ-dQns_PFIZ89Wy-w",
        "Video_ID": "r71khfg9ue4",
        "View_Count": "92",
        "Published_At": "2022-06-19T22:32:26Z",
        "Video_Title": "Worry is unbelief | Sorge ist Unglaube"
    },
    {
        "Channel_ID": "UC_-LsoQ-dQns_PFIZ89Wy-w",
        "Video_ID": "y-NmQrGq1jQ",
        "View_Count": "93",
        "Published_At": "2022-06-12T22:28:32Z",
        "Video_Title": "Worauf schaust du? | What are you looking at?"
    },
    {
        "Channel_ID": "UC_-LsoQ-dQns_PFIZ89Wy-w",
        "Video_ID": "VGlOS6etBtM",
        "View_Count": "87",
        "Published_At": "2022-06-05T22:53:40Z",
        "Video_Title": "Baue meine Gemeinde | Build my church"
    },
    {
        "Channel_ID": "UC_-LsoQ-dQns_PFIZ89Wy-w",
        "Video_ID": "dtraA46LMuY",
        "View_Count": "83",
        "Published_At": "2022-05-29T22:41:08Z",
        "Video_Title": "Identit\u00e4t- eine Frage von Beziehung | Identity- a relational thing"
    },
    {
        "Channel_ID": "UC_-LsoQ-dQns_PFIZ89Wy-w",
        "Video_ID": "GuhYk7butMA",
        "View_Count": "93",
        "Published_At": "2022-05-22T22:27:48Z",
        "Video_Title": "Wirksam beten | Praying effectively"
    },
    {
        "Channel_ID": "UC_-LsoQ-dQns_PFIZ89Wy-w",
        "Video_ID": "ODLLw7PzIQ4",
        "View_Count": "179",
        "Published_At": "2022-05-15T23:13:11Z",
        "Video_Title": "Pornography | Pornografie"
    },
    {
        "Channel_ID": "UC_-LsoQ-dQns_PFIZ89Wy-w",
        "Video_ID": "dog-L831oH8",
        "View_Count": "73",
        "Published_At": "2022-05-08T22:55:39Z",
        "Video_Title": "The basic method of witnessing | Die grundlegende Methode des Zeugnisgebens"
    },
    {
        "Channel_ID": "UC_-LsoQ-dQns_PFIZ89Wy-w",
        "Video_ID": "4l9kQ_7l8Zo",
        "View_Count": "107",
        "Published_At": "2022-05-01T23:03:40Z",
        "Video_Title": "Zeugnis Gottesdienst // Testimony church service"
    },
    {
        "Channel_ID": "UC_-LsoQ-dQns_PFIZ89Wy-w",
        "Video_ID": "_QRqGN1A-s0",
        "View_Count": "89",
        "Published_At": "2022-04-24T22:43:42Z",
        "Video_Title": "The basic method of witnessing | Die grundlegende Methode des Zeugnisgebens"
    },
    {
        "Channel_ID": "UC_-LsoQ-dQns_PFIZ89Wy-w",
        "Video_ID": "YiVFw45q4vw",
        "View_Count": "80",
        "Published_At": "2022-04-17T23:02:11Z",
        "Video_Title": "Jesus ist aus dem Grab auferstanden | Jesus is risen from the grave"
    },
    {
        "Channel_ID": "UC_-LsoQ-dQns_PFIZ89Wy-w",
        "Video_ID": "fdG8okoMdd4",
        "View_Count": "80",
        "Published_At": "2022-04-10T22:54:24Z",
        "Video_Title": "Ein Schnappschuss von Gott | A snapshot of God"
    },
    {
        "Channel_ID": "UC_-LsoQ-dQns_PFIZ89Wy-w",
        "Video_ID": "8yDrfZ3yZW0",
        "View_Count": "117",
        "Published_At": "2022-04-03T22:21:59Z",
        "Video_Title": "Ein erf\u00fclltes Leben | A fulfilled life"
    },
    {
        "Channel_ID": "UC_-LsoQ-dQns_PFIZ89Wy-w",
        "Video_ID": "gU-lLgzCt9M",
        "View_Count": "99",
        "Published_At": "2022-03-27T22:50:29Z",
        "Video_Title": "Sei Du, sei authentisch | Be you, be authentic"
    },
    {
        "Channel_ID": "UC_-LsoQ-dQns_PFIZ89Wy-w",
        "Video_ID": "xZzcvUSwzhc",
        "View_Count": "78",
        "Published_At": "2022-03-20T23:55:20Z",
        "Video_Title": "Sharing the gospel with others Part 3 | Das Evangelium mit anderen teilen Teil 3"
    },
    {
        "Channel_ID": "UC_-LsoQ-dQns_PFIZ89Wy-w",
        "Video_ID": "xLfx8bXemvk",
        "View_Count": "99",
        "Published_At": "2022-03-13T23:58:43Z",
        "Video_Title": "Sharing the gospel with others Part 2 | Das Evangelium mit anderen teilen Teil 2"
    },
    {
        "Channel_ID": "UC_-LsoQ-dQns_PFIZ89Wy-w",
        "Video_ID": "Pv9yck-lQQo",
        "View_Count": "114",
        "Published_At": "2022-03-06T23:50:11Z",
        "Video_Title": "Sharing the gospel with others | Das Evangelium mit anderen teilen"
    },
    {
        "Channel_ID": "UC_-LsoQ-dQns_PFIZ89Wy-w",
        "Video_ID": "a1XT5PNIfgk",
        "View_Count": "84",
        "Published_At": "2022-02-27T23:55:12Z",
        "Video_Title": "Living an effective christian life Part 2 | Ein effektives christliches Leben f\u00fchren Teil 2"
    },
    {
        "Channel_ID": "UC_-LsoQ-dQns_PFIZ89Wy-w",
        "Video_ID": "RQ77eIP8x8c",
        "View_Count": "122",
        "Published_At": "2022-02-20T23:50:30Z",
        "Video_Title": "The power of God's Word Part 2 | Die Kraft des Wort Gottes Teil 2"
    },
    {
        "Channel_ID": "UC_-LsoQ-dQns_PFIZ89Wy-w",
        "Video_ID": "lJOCQYMwdoE",
        "View_Count": "184",
        "Published_At": "2022-02-13T23:35:41Z",
        "Video_Title": "The power of God's Word | Die Kraft des Wort Gottes"
    },
    {
        "Channel_ID": "UC_-LsoQ-dQns_PFIZ89Wy-w",
        "Video_ID": "1Jn2I03Qeos",
        "View_Count": "121",
        "Published_At": "2022-02-06T23:52:33Z",
        "Video_Title": "My refuge and great physician | Meine Zuflucht und mein gro\u00dfer Arzt"
    },
    {
        "Channel_ID": "UC_-LsoQ-dQns_PFIZ89Wy-w",
        "Video_ID": "Jqf83MGIxn8",
        "View_Count": "136",
        "Published_At": "2022-01-30T23:58:27Z",
        "Video_Title": "Living an effective christian life | Ein effektives christliches Leben"
    },
    {
        "Channel_ID": "UC_-LsoQ-dQns_PFIZ89Wy-w",
        "Video_ID": "EzVaPAwMtjc",
        "View_Count": "91",
        "Published_At": "2022-01-23T23:57:35Z",
        "Video_Title": "What are You living for? Part 2 | Wof\u00fcr lebst Du? Teil 2"
    },
    {
        "Channel_ID": "UC_-LsoQ-dQns_PFIZ89Wy-w",
        "Video_ID": "v8jn0msB3FA",
        "View_Count": "111",
        "Published_At": "2022-01-16T23:51:43Z",
        "Video_Title": "What are You living for? | Wof\u00fcr lebst Du?"
    },
    {
        "Channel_ID": "UC_-LsoQ-dQns_PFIZ89Wy-w",
        "Video_ID": "R3ZyZzg-tvA",
        "View_Count": "75",
        "Published_At": "2022-01-09T23:53:06Z",
        "Video_Title": "At all times God is dependable part 2 | Auf Gott ist immer Verlass Teil 2"
    },
    {
        "Channel_ID": "UC_-LsoQ-dQns_PFIZ89Wy-w",
        "Video_ID": "GnJg-c4yjNs",
        "View_Count": "115",
        "Published_At": "2022-01-03T00:02:05Z",
        "Video_Title": "At all times God is dependable | Auf Gott ist immer Verlass"
    },
    {
        "Channel_ID": "UC_-LsoQ-dQns_PFIZ89Wy-w",
        "Video_ID": "2H8DpwvYMNM",
        "View_Count": "289",
        "Published_At": "2022-01-01T11:31:15Z",
        "Video_Title": "New Year's Eve church service | Silvestergottesdienst"
    },
    {
        "Channel_ID": "UC_-LsoQ-dQns_PFIZ89Wy-w",
        "Video_ID": "EWvMeGH2b90",
        "View_Count": "193",
        "Published_At": "2021-12-26T23:58:17Z",
        "Video_Title": "Be a light | Sei ein Licht"
    },
    {
        "Channel_ID": "UC_-LsoQ-dQns_PFIZ89Wy-w",
        "Video_ID": "Jgu5DKRL-lU",
        "View_Count": "148",
        "Published_At": "2021-12-20T00:34:33Z",
        "Video_Title": "Testimony church service | Zeugnis Gottesdienst"
    },
    {
        "Channel_ID": "UC_-LsoQ-dQns_PFIZ89Wy-w",
        "Video_ID": "f3HiyFxYV_A",
        "View_Count": "56",
        "Published_At": "2021-12-13T00:03:27Z",
        "Video_Title": "Choose God's wisdom // Erw\u00e4hle Gottes Weisheit"
    },
    {
        "Channel_ID": "UC_-LsoQ-dQns_PFIZ89Wy-w",
        "Video_ID": "nQPndsd0K4Q",
        "View_Count": "73",
        "Published_At": "2021-12-12T22:51:06Z",
        "Video_Title": "Choose God's wisdom // Erw\u00e4hle Gottes Weisheit"
    },
    {
        "Channel_ID": "UC_-LsoQ-dQns_PFIZ89Wy-w",
        "Video_ID": "VjD_YhFLhO0",
        "View_Count": "105",
        "Published_At": "2021-12-06T00:02:56Z",
        "Video_Title": "Be grateful for everything at anytime | Sei zu jeder zeit f\u00fcr alles dankbar"
    },
    {
        "Channel_ID": "UC_-LsoQ-dQns_PFIZ89Wy-w",
        "Video_ID": "6v87_CmDANI",
        "View_Count": "110",
        "Published_At": "2021-11-28T23:55:00Z",
        "Video_Title": "Trusting God in the darkness | Gott vertrauen, wenn es dunkel ist"
    },
    {
        "Channel_ID": "UC_-LsoQ-dQns_PFIZ89Wy-w",
        "Video_ID": "sPloigqMZio",
        "View_Count": "72",
        "Published_At": "2021-11-21T23:44:35Z",
        "Video_Title": "Reigning in life by the name | Im Leben durch den Namen regieren"
    },
    {
        "Channel_ID": "UC_-LsoQ-dQns_PFIZ89Wy-w",
        "Video_ID": "zeDVKtnijdQ",
        "View_Count": "97",
        "Published_At": "2021-11-15T00:01:20Z",
        "Video_Title": "Clothe yourself with love | Kleide dich mit Liebe"
    },
    {
        "Channel_ID": "UC_-LsoQ-dQns_PFIZ89Wy-w",
        "Video_ID": "Jpcoa_Q1X80",
        "View_Count": "85",
        "Published_At": "2021-11-07T23:43:47Z",
        "Video_Title": "Your future is assured | Deine Zukunft ist gesichert"
    },
    {
        "Channel_ID": "UC_-LsoQ-dQns_PFIZ89Wy-w",
        "Video_ID": "PjKjhbGLvu8",
        "View_Count": "71",
        "Published_At": "2021-10-31T23:54:25Z",
        "Video_Title": "Pretending vs. believing Part 4 | Selbstt\u00e4uschung vs. Glauben Part 4"
    },
    {
        "Channel_ID": "UC_-LsoQ-dQns_PFIZ89Wy-w",
        "Video_ID": "hv9O4CduRSA",
        "View_Count": "113",
        "Published_At": "2021-10-24T22:59:29Z",
        "Video_Title": "Pretending vs. believing Part 3 | Selbstt\u00e4uschung vs. Glauben Part 3"
    },
    {
        "Channel_ID": "UC_-LsoQ-dQns_PFIZ89Wy-w",
        "Video_ID": "ZtGGSbA75Sk",
        "View_Count": "76",
        "Published_At": "2021-10-17T22:46:13Z",
        "Video_Title": "Pretending vs. believing Part 2 | Selbstt\u00e4uschung vs. Glauben Part 2"
    },
    {
        "Channel_ID": "UC_-LsoQ-dQns_PFIZ89Wy-w",
        "Video_ID": "5iGJ49hQXmQ",
        "View_Count": "119",
        "Published_At": "2021-10-10T22:41:41Z",
        "Video_Title": "Who do you see in your problems? | An wen wendest Du dich in deinen Problemen?"
    },
    {
        "Channel_ID": "UC_-LsoQ-dQns_PFIZ89Wy-w",
        "Video_ID": "BC2o8MPmeis",
        "View_Count": "86",
        "Published_At": "2021-10-03T22:54:07Z",
        "Video_Title": "Pretending vs. believing | Selbstt\u00e4uschung vs. Glauben"
    },
    {
        "Channel_ID": "UC_-LsoQ-dQns_PFIZ89Wy-w",
        "Video_ID": "zuVtIHLp-Kg",
        "View_Count": "69",
        "Published_At": "2021-09-26T22:56:38Z",
        "Video_Title": "Our daily victory in Jesus Name Part 2 | Unser t\u00e4glicher Sieg in Jesus Namen Teil 2"
    },
    {
        "Channel_ID": "UC_-LsoQ-dQns_PFIZ89Wy-w",
        "Video_ID": "LKEwoQVjVlQ",
        "View_Count": "98",
        "Published_At": "2021-09-19T22:41:13Z",
        "Video_Title": "Our daily victory in Jesus Name | Unser t\u00e4glicher Sieg in Jesus Namen"
    },
    {
        "Channel_ID": "UC_-LsoQ-dQns_PFIZ89Wy-w",
        "Video_ID": "X7AIYYrXGFA",
        "View_Count": "85",
        "Published_At": "2021-09-12T22:31:24Z",
        "Video_Title": "What kind of people? | Welche Art von Mensch?"
    },
    {
        "Channel_ID": "UC_-LsoQ-dQns_PFIZ89Wy-w",
        "Video_ID": "qaFFn1UK_aE",
        "View_Count": "88",
        "Published_At": "2021-09-05T23:04:30Z",
        "Video_Title": "Gods constant presence | Gottes st\u00e4ndige Gegenwart"
    },
    {
        "Channel_ID": "UC_-LsoQ-dQns_PFIZ89Wy-w",
        "Video_ID": "gjs0U1eV-GY",
        "View_Count": "83",
        "Published_At": "2021-08-29T23:02:19Z",
        "Video_Title": "Do everything in the name | Tue alles in dem Namen"
    },
    {
        "Channel_ID": "UC_-LsoQ-dQns_PFIZ89Wy-w",
        "Video_ID": "R-opN8Ugl64",
        "View_Count": "84",
        "Published_At": "2021-08-22T22:38:48Z",
        "Video_Title": "Keep on going | Geh weiter"
    },
    {
        "Channel_ID": "UC_-LsoQ-dQns_PFIZ89Wy-w",
        "Video_ID": "46pgVi2UOqw",
        "View_Count": "79",
        "Published_At": "2021-08-15T22:49:57Z",
        "Video_Title": "Gott k\u00fcmmert sich zu jeder Zeit | God cares all time"
    },
    {
        "Channel_ID": "UC_-LsoQ-dQns_PFIZ89Wy-w",
        "Video_ID": "qbuwQVYaWnk",
        "View_Count": "220",
        "Published_At": "2021-08-08T23:02:33Z",
        "Video_Title": "Kenne Gottes Liebe und widerstehe dem Teufel! | Know God's love and resist the devil"
    },
    {
        "Channel_ID": "UC_-LsoQ-dQns_PFIZ89Wy-w",
        "Video_ID": "saDtA4n98Nw",
        "View_Count": "93",
        "Published_At": "2021-08-01T22:47:48Z",
        "Video_Title": "Gottes unersch\u00fctterliche Liebe versagt nie | God's steadfast love never fails"
    },
    {
        "Channel_ID": "UC_-LsoQ-dQns_PFIZ89Wy-w",
        "Video_ID": "qYNBGIYA4nQ",
        "View_Count": "96",
        "Published_At": "2021-07-25T23:05:54Z",
        "Video_Title": "Glaube daran, dass du wertvoll und einzigartig bist | Believe you are valuable and unique"
    },
    {
        "Channel_ID": "UC_-LsoQ-dQns_PFIZ89Wy-w",
        "Video_ID": "jvPGDVm0Hqo",
        "View_Count": "94",
        "Published_At": "2021-07-18T22:47:33Z",
        "Video_Title": "Wie hat Jesus seinen Namen erhalten? Teil 5 | How did Jesus obtain His name? Part 5"
    },
    {
        "Channel_ID": "UC_-LsoQ-dQns_PFIZ89Wy-w",
        "Video_ID": "A_ShoICzt3c",
        "View_Count": "119",
        "Published_At": "2021-07-11T22:26:50Z",
        "Video_Title": "Ermutigung | Encouragement"
    },
    {
        "Channel_ID": "UC_-LsoQ-dQns_PFIZ89Wy-w",
        "Video_ID": "SY5ox-jVsQE",
        "View_Count": "100",
        "Published_At": "2021-07-04T22:23:45Z",
        "Video_Title": "How do you look at death? | Wie siehst du den Tod?"
    },
    {
        "Channel_ID": "UC_-LsoQ-dQns_PFIZ89Wy-w",
        "Video_ID": "1O5YLZZLZ90",
        "View_Count": "88",
        "Published_At": "2021-06-28T09:07:46Z",
        "Video_Title": "Wie hat Jesus seinen Namen erhalten? Teil 4 | How did Jesus obtains his name? Part 4"
    },
    {
        "Channel_ID": "UC_-LsoQ-dQns_PFIZ89Wy-w",
        "Video_ID": "uVTVuuKUIXQ",
        "View_Count": "95",
        "Published_At": "2021-06-20T22:29:09Z",
        "Video_Title": "Wie hat Jesus seinen Namen erhalten? Teil 3 | How did Jesus obtains his name? Part 3"
    },
    {
        "Channel_ID": "UC_-LsoQ-dQns_PFIZ89Wy-w",
        "Video_ID": "RutxbTUIisk",
        "View_Count": "57",
        "Published_At": "2021-06-13T22:50:32Z",
        "Video_Title": "Wie hat Jesus seinen Namen erhalten? Teil 2 | How did Jesus obtains his name? Part 2"
    },
    {
        "Channel_ID": "UC_-LsoQ-dQns_PFIZ89Wy-w",
        "Video_ID": "wWQvP9yTQmw",
        "View_Count": "69",
        "Published_At": "2021-06-06T22:39:24Z",
        "Video_Title": "Wie hat Jesus seinen Namen erhalten? | How did Jesus obtains his name?"
    },
    {
        "Channel_ID": "UC_-LsoQ-dQns_PFIZ89Wy-w",
        "Video_ID": "SypIyh3BWuI",
        "View_Count": "79",
        "Published_At": "2021-05-30T23:09:03Z",
        "Video_Title": "Warum ist die lokale Gemeinde wichtig? | Why is the local church important?"
    },
    {
        "Channel_ID": "UC_-LsoQ-dQns_PFIZ89Wy-w",
        "Video_ID": "tfjUDEzyifo",
        "View_Count": "78",
        "Published_At": "2021-05-23T22:41:59Z",
        "Video_Title": "Die Liebe Gottes durch dich | The Love of god through you"
    },
    {
        "Channel_ID": "UC_-LsoQ-dQns_PFIZ89Wy-w",
        "Video_ID": "WWp3qSX5Yrk",
        "View_Count": "79",
        "Published_At": "2021-05-16T22:47:42Z",
        "Video_Title": "Dauerhaft f\u00fcr immer gerettet | Permanently rescued forever"
    },
    {
        "Channel_ID": "UC_-LsoQ-dQns_PFIZ89Wy-w",
        "Video_ID": "rkRIaUjbKgk",
        "View_Count": "87",
        "Published_At": "2021-05-09T22:38:53Z",
        "Video_Title": "Du und der Name Jesus | You and the name of Jesus"
    },
    {
        "Channel_ID": "UC_-LsoQ-dQns_PFIZ89Wy-w",
        "Video_ID": "ZCbtoo0J5ho",
        "View_Count": "91",
        "Published_At": "2021-05-02T22:35:27Z",
        "Video_Title": "Wie man richtig betet, um Antwort zu bekommen Teil 3 | How to pray and get an answer part 3"
    },
    {
        "Channel_ID": "UC_-LsoQ-dQns_PFIZ89Wy-w",
        "Video_ID": "DtAvMOvixQQ",
        "View_Count": "65",
        "Published_At": "2021-04-25T22:31:05Z",
        "Video_Title": "Wie man richtig betet, um Antwort zu bekommen Teil 2 | How to pray and get an answer part 2"
    },
    {
        "Channel_ID": "UC_-LsoQ-dQns_PFIZ89Wy-w",
        "Video_ID": "YHZkOWe7Q54",
        "View_Count": "67",
        "Published_At": "2021-04-18T22:30:14Z",
        "Video_Title": "Wie man richtig betet, um Antwort zu bekommen | How to pray and get an answer"
    },
    {
        "Channel_ID": "UC_-LsoQ-dQns_PFIZ89Wy-w",
        "Video_ID": "bQBh0yKUWa0",
        "View_Count": "64",
        "Published_At": "2021-04-11T22:48:50Z",
        "Video_Title": "Leben im himmlischen Bereich Teil 2 | Living in the heavenly realm part 2"
    },
    {
        "Channel_ID": "UC_-LsoQ-dQns_PFIZ89Wy-w",
        "Video_ID": "SPe210g6hk0",
        "View_Count": "109",
        "Published_At": "2021-04-04T22:52:59Z",
        "Video_Title": "Leben im himmlischen Bereich | Living in the heavenly realm"
    },
    {
        "Channel_ID": "UC_-LsoQ-dQns_PFIZ89Wy-w",
        "Video_ID": "g13bWNDShXk",
        "View_Count": "103",
        "Published_At": "2021-03-28T22:50:46Z",
        "Video_Title": "Den menschlichen Geist entwickeln - Teil 5 | Developing the human spirit - Part 5"
    },
    {
        "Channel_ID": "UC_-LsoQ-dQns_PFIZ89Wy-w",
        "Video_ID": "ncSJOTYduJA",
        "View_Count": "88",
        "Published_At": "2021-03-21T23:42:14Z",
        "Video_Title": "Den menschlichen Geist entwickeln - Teil 4 | Developing the human spirit - Part 4"
    },
    {
        "Channel_ID": "UC_-LsoQ-dQns_PFIZ89Wy-w",
        "Video_ID": "2P-J2L8YEAA",
        "View_Count": "120",
        "Published_At": "2021-03-14T23:32:21Z",
        "Video_Title": "Den menschlichen Geist entwickeln - Teil 3 | Developing the human spirit - Part 3"
    },
    {
        "Channel_ID": "UC_-LsoQ-dQns_PFIZ89Wy-w",
        "Video_ID": "ZTJ-P3XsyBM",
        "View_Count": "95",
        "Published_At": "2021-03-07T23:39:19Z",
        "Video_Title": "Den menschlichen Geist entwickeln - Teil 2 | Developing the human spirit - Part 2"
    },
    {
        "Channel_ID": "UC_-LsoQ-dQns_PFIZ89Wy-w",
        "Video_ID": "QkVnQgP5jFE",
        "View_Count": "123",
        "Published_At": "2021-02-28T23:35:41Z",
        "Video_Title": "Den menschlichen Geist entwickeln | Developing the human spirit"
    },
    {
        "Channel_ID": "UC_-LsoQ-dQns_PFIZ89Wy-w",
        "Video_ID": "s7kSh-4Dwos",
        "View_Count": "109",
        "Published_At": "2021-02-21T23:31:12Z",
        "Video_Title": "Gehorsam: der Schl\u00fcssel zu einem siegreichen Leben | Obedience: the key to a victorious life"
    },
    {
        "Channel_ID": "UC_-LsoQ-dQns_PFIZ89Wy-w",
        "Video_ID": "omqPan8Ira0",
        "View_Count": "128",
        "Published_At": "2021-02-15T00:05:22Z",
        "Video_Title": "Gottes Liebe f\u00fcr dich | God's love for you"
    },
    {
        "Channel_ID": "UC_-LsoQ-dQns_PFIZ89Wy-w",
        "Video_ID": "ETLA8ymDhG4",
        "View_Count": "192",
        "Published_At": "2021-02-08T00:09:18Z",
        "Video_Title": "Erh\u00f6rte Gebete: eine absolute Garantie | Answered prayers: an absolute guarantee"
    },
    {
        "Channel_ID": "UC_-LsoQ-dQns_PFIZ89Wy-w",
        "Video_ID": "V9tFtCnwIXo",
        "View_Count": "115",
        "Published_At": "2021-01-31T23:49:57Z",
        "Video_Title": "Put God first | Gott an erste Stelle setzen"
    },
    {
        "Channel_ID": "UC_-LsoQ-dQns_PFIZ89Wy-w",
        "Video_ID": "YPNV6G2R5tI",
        "View_Count": "126",
        "Published_At": "2021-01-24T23:57:51Z",
        "Video_Title": "The Holy Spirit my friend -Part 2-| Der Heilige Geist mein Freund -Teil 2-"
    },
    {
        "Channel_ID": "UC_-LsoQ-dQns_PFIZ89Wy-w",
        "Video_ID": "jXrVgH380Qo",
        "View_Count": "120",
        "Published_At": "2021-01-17T23:59:57Z",
        "Video_Title": "The Holy Spirit my friend | Der Heilige Geist mein Freund"
    },
    {
        "Channel_ID": "UC_-LsoQ-dQns_PFIZ89Wy-w",
        "Video_ID": "P767CrhOwWo",
        "View_Count": "214",
        "Published_At": "2021-01-10T23:59:03Z",
        "Video_Title": "How to live in the last days - Teil 2 - | Wie lebt man in den letzten Tagen - Part 2 -"
    },
    {
        "Channel_ID": "UC_-LsoQ-dQns_PFIZ89Wy-w",
        "Video_ID": "H-sGHDI4Mcc",
        "View_Count": "115",
        "Published_At": "2021-01-03T23:43:18Z",
        "Video_Title": "How to live in the last days | Wie lebt man in den letzten Tagen"
    },
    {
        "Channel_ID": "UC_-LsoQ-dQns_PFIZ89Wy-w",
        "Video_ID": "UBHVr4jDnVU",
        "View_Count": "499",
        "Published_At": "2021-01-01T07:00:17Z",
        "Video_Title": "Worship Night"
    },
    {
        "Channel_ID": "UC_-LsoQ-dQns_PFIZ89Wy-w",
        "Video_ID": "oTdH2XdlZnk",
        "View_Count": "118",
        "Published_At": "2020-12-27T23:47:55Z",
        "Video_Title": "From total lockdown to total victory | Vom totalen Lockdown zum totalen Sieg"
    },
    {
        "Channel_ID": "UC_-LsoQ-dQns_PFIZ89Wy-w",
        "Video_ID": "S4AUzy4sQZQ",
        "View_Count": "142",
        "Published_At": "2020-12-20T23:46:50Z",
        "Video_Title": "Christ has rescued us | Christus hat uns errettet"
    },
    {
        "Channel_ID": "UC_-LsoQ-dQns_PFIZ89Wy-w",
        "Video_ID": "PevL-qdV61k",
        "View_Count": "127",
        "Published_At": "2020-12-14T00:17:50Z",
        "Video_Title": "Zeugnisse Gottesdienst | Testimony church service"
    },
    {
        "Channel_ID": "UC_-LsoQ-dQns_PFIZ89Wy-w",
        "Video_ID": "6KQ4GlTVv3U",
        "View_Count": "61",
        "Published_At": "2020-12-06T23:55:38Z",
        "Video_Title": "Sei dankbar f\u00fcr alles zu jederzeit | Be thankful for anything at anytime"
    },
    {
        "Channel_ID": "UC_-LsoQ-dQns_PFIZ89Wy-w",
        "Video_ID": "jjoHCoGbARw",
        "View_Count": "82",
        "Published_At": "2020-11-29T23:52:44Z",
        "Video_Title": "Glaube setzt Gottes Kraft frei - Teil 3c | Faith releases God's power - Part 3c"
    },
    {
        "Channel_ID": "UC_-LsoQ-dQns_PFIZ89Wy-w",
        "Video_ID": "cZrsUc9Ft6E",
        "View_Count": "105",
        "Published_At": "2020-11-22T23:49:58Z",
        "Video_Title": "Glaube setzt Gottes Kraft frei - Teil 3b | Faith releases God's power - Part 3b"
    },
    {
        "Channel_ID": "UC_-LsoQ-dQns_PFIZ89Wy-w",
        "Video_ID": "s2cEv2UYXwo",
        "View_Count": "125",
        "Published_At": "2020-11-15T23:55:48Z",
        "Video_Title": "Glaube setzt Gottes Kraft frei - Teil 3 | Faith releases God's power - Part 3"
    },
    {
        "Channel_ID": "UC_-LsoQ-dQns_PFIZ89Wy-w",
        "Video_ID": "9UZI_hXyC1Y",
        "View_Count": "95",
        "Published_At": "2020-11-09T00:35:30Z",
        "Video_Title": "Glaube setzt Gottes Kraft frei - Teil 2b | Faith releases God's power - Part 2b"
    },
    {
        "Channel_ID": "UC_-LsoQ-dQns_PFIZ89Wy-w",
        "Video_ID": "WVMXYcLl_Xw",
        "View_Count": "125",
        "Published_At": "2020-11-01T23:44:59Z",
        "Video_Title": "Das Leben ist ein Rennen oder Marathon | Life is a race or marathon"
    },
    {
        "Channel_ID": "UC_-LsoQ-dQns_PFIZ89Wy-w",
        "Video_ID": "GpQL2JTxa5g",
        "View_Count": "79",
        "Published_At": "2020-10-25T23:48:51Z",
        "Video_Title": "Glaube setzt Gottes Kraft frei - Teil 2 | Faith releases God's power - Part 2"
    },
    {
        "Channel_ID": "UC_-LsoQ-dQns_PFIZ89Wy-w",
        "Video_ID": "ofMsLGDl96w",
        "View_Count": "123",
        "Published_At": "2020-10-18T22:51:54Z",
        "Video_Title": "Glaube setzt Gottes Kraft frei - Teil 1c | Faith releases God's power - Part 1c"
    },
    {
        "Channel_ID": "UC_-LsoQ-dQns_PFIZ89Wy-w",
        "Video_ID": "1mUElWXvRSA",
        "View_Count": "142",
        "Published_At": "2020-10-11T22:40:12Z",
        "Video_Title": "Glaube setzt Gottes Kraft frei - Teil 1b | Faith releases God's power - Part 1b"
    },
    {
        "Channel_ID": "UC_-LsoQ-dQns_PFIZ89Wy-w",
        "Video_ID": "LTv0OhxAhts",
        "View_Count": "107",
        "Published_At": "2020-10-04T10:30:41Z",
        "Video_Title": "Familiengottesdienst | Family Church Service"
    },
    {
        "Channel_ID": "UC_-LsoQ-dQns_PFIZ89Wy-w",
        "Video_ID": "ZldBqBWcLRg",
        "View_Count": "85",
        "Published_At": "2020-09-27T23:00:01Z",
        "Video_Title": "Geistliche Reife Teil 2 | Spiritual maturity Part 2"
    },
    {
        "Channel_ID": "UC_-LsoQ-dQns_PFIZ89Wy-w",
        "Video_ID": "JjXuerFq7vM",
        "View_Count": "218",
        "Published_At": "2020-09-20T11:10:28Z",
        "Video_Title": "Geistliche Reife | Spiritual maturity"
    },
    {
        "Channel_ID": "UC_-LsoQ-dQns_PFIZ89Wy-w",
        "Video_ID": "jLYcFP3bb9I",
        "View_Count": "185",
        "Published_At": "2020-09-13T22:45:10Z",
        "Video_Title": "Glaube setzt Gottes Kraft frei | Faith releases God's power"
    },
    {
        "Channel_ID": "UC_-LsoQ-dQns_PFIZ89Wy-w",
        "Video_ID": "WjBRKc0oZyU",
        "View_Count": "124",
        "Published_At": "2020-09-06T11:02:26Z",
        "Video_Title": "Familiegottesdienst: Zeugnisse | Family church Service: Testimony"
    },
    {
        "Channel_ID": "UC_-LsoQ-dQns_PFIZ89Wy-w",
        "Video_ID": "UrciX7bKIiE",
        "View_Count": "120",
        "Published_At": "2020-08-30T22:42:34Z",
        "Video_Title": "Glaube kann deine Welt ver\u00e4ndern! Teil 2 | Faith Can Change Your World! Part 2"
    },
    {
        "Channel_ID": "UC_-LsoQ-dQns_PFIZ89Wy-w",
        "Video_ID": "IsYcW4M2qmw",
        "View_Count": "99",
        "Published_At": "2020-08-23T22:39:54Z",
        "Video_Title": "Glaube kann deine Welt ver\u00e4ndern! Teil 1b | Faith Can Change Your World! Part 1b"
    },
    {
        "Channel_ID": "UC_-LsoQ-dQns_PFIZ89Wy-w",
        "Video_ID": "8V5yKDtZ1j4",
        "View_Count": "100",
        "Published_At": "2020-08-16T20:49:03Z",
        "Video_Title": "Glaube kann deine Welt ver\u00e4ndern! Teil 1 | Faith can change your World! Part 1"
    },
    {
        "Channel_ID": "UC_-LsoQ-dQns_PFIZ89Wy-w",
        "Video_ID": "vlxCHepSyLI",
        "View_Count": "110",
        "Published_At": "2020-08-09T22:28:19Z",
        "Video_Title": "Christus lebt in dir Teil 6 | Christ lives in you Part 6"
    },
    {
        "Channel_ID": "UC_-LsoQ-dQns_PFIZ89Wy-w",
        "Video_ID": "Dmm6RVptkNA",
        "View_Count": "87",
        "Published_At": "2020-08-02T22:36:26Z",
        "Video_Title": "Christus lebt in dir Teil 5 | Christ lives in you Part 5"
    },
    {
        "Channel_ID": "UC_-LsoQ-dQns_PFIZ89Wy-w",
        "Video_ID": "45brSFWauxU",
        "View_Count": "30",
        "Published_At": "2020-07-31T19:02:28Z",
        "Video_Title": "Die Wichtigkeit deiner Wortwahl | The importance of your words"
    },
    {
        "Channel_ID": "UC_-LsoQ-dQns_PFIZ89Wy-w",
        "Video_ID": "xnvgaP9Nv3s",
        "View_Count": "93",
        "Published_At": "2020-07-26T22:32:09Z",
        "Video_Title": "Christus lebt in dir Teil 4 | Christ lives in you Part 4"
    },
    {
        "Channel_ID": "UC_-LsoQ-dQns_PFIZ89Wy-w",
        "Video_ID": "8b9cvRvh8oU",
        "View_Count": "17",
        "Published_At": "2020-07-25T12:08:09Z",
        "Video_Title": "Gott dein Artzt Teil XIV | God your physician part XIV"
    },
    {
        "Channel_ID": "UC_-LsoQ-dQns_PFIZ89Wy-w",
        "Video_ID": "YF8cTOzaT_w",
        "View_Count": "149",
        "Published_At": "2020-07-19T22:41:55Z",
        "Video_Title": "Christus lebt in dir Teil 3 | Christ lives in you Part 3"
    },
    {
        "Channel_ID": "UC_-LsoQ-dQns_PFIZ89Wy-w",
        "Video_ID": "OGGHUMxpSwQ",
        "View_Count": "104",
        "Published_At": "2020-07-12T22:37:20Z",
        "Video_Title": "Christus lebt in dir Teil 2 | Christ lives in you Part 2"
    },
    {
        "Channel_ID": "UC_-LsoQ-dQns_PFIZ89Wy-w",
        "Video_ID": "UduzHpZXshU",
        "View_Count": "126",
        "Published_At": "2020-07-05T22:31:37Z",
        "Video_Title": "Christus lebt in dir | Christ lives in you"
    },
    {
        "Channel_ID": "UC_-LsoQ-dQns_PFIZ89Wy-w",
        "Video_ID": "1apQxPsrCF4",
        "View_Count": "228",
        "Published_At": "2020-06-28T22:37:43Z",
        "Video_Title": "Verfolgung bringt Ver\u00e4nderung und Wachstum | Persecution brings change and increase"
    },
    {
        "Channel_ID": "UC_-LsoQ-dQns_PFIZ89Wy-w",
        "Video_ID": "oQCDLM9cotE",
        "View_Count": "33",
        "Published_At": "2020-06-26T16:06:23Z",
        "Video_Title": "Gottes menschliche Sch\u00f6pfung | God's Human Race"
    },
    {
        "Channel_ID": "UC_-LsoQ-dQns_PFIZ89Wy-w",
        "Video_ID": "20pWa6fIBwI",
        "View_Count": "17",
        "Published_At": "2020-06-19T20:34:27Z",
        "Video_Title": "Gott dein Arzt Teil XI | God your physician PArt XI"
    },
    {
        "Channel_ID": "UC_-LsoQ-dQns_PFIZ89Wy-w",
        "Video_ID": "hVqgSJOy330",
        "View_Count": "20",
        "Published_At": "2020-06-14T11:19:07Z",
        "Video_Title": "Wer auch immer soll haben was auch immer | Whosoever shall have whatsoever"
    },
    {
        "Channel_ID": "UC_-LsoQ-dQns_PFIZ89Wy-w",
        "Video_ID": "ezBvqbPtCoI",
        "View_Count": "6",
        "Published_At": "2020-06-07T15:51:15Z",
        "Video_Title": "Siegreiches Leben Teil 2 | Victorious Life Part 2"
    },
    {
        "Channel_ID": "UC_-LsoQ-dQns_PFIZ89Wy-w",
        "Video_ID": "5Z-ZlaS79HM",
        "View_Count": "12",
        "Published_At": "2020-06-05T21:41:33Z",
        "Video_Title": "Gott dein Arzt Teil X | God your physician Part X"
    },
    {
        "Channel_ID": "UC_-LsoQ-dQns_PFIZ89Wy-w",
        "Video_ID": "o-uh6ic-DEY",
        "View_Count": "17",
        "Published_At": "2020-06-03T08:03:08Z",
        "Video_Title": "Die gro\u00dfe Ausr\u00fcstung | The great Equipment"
    },
    {
        "Channel_ID": "UC_-LsoQ-dQns_PFIZ89Wy-w",
        "Video_ID": "zelxnpt63G0",
        "View_Count": "3",
        "Published_At": "2020-06-02T23:05:19Z",
        "Video_Title": "Gott dein Arzt Teil IX | God your physician Part IX"
    },
    {
        "Channel_ID": "UC_-LsoQ-dQns_PFIZ89Wy-w",
        "Video_ID": "LKdpAw9Uxdo",
        "View_Count": "37",
        "Published_At": "2020-05-28T20:31:53Z",
        "Video_Title": "Schlie\u00dfe Friede mit Gott | Make Peace with God"
    },
    {
        "Channel_ID": "UC_-LsoQ-dQns_PFIZ89Wy-w",
        "Video_ID": "UVm5CrseJMg",
        "View_Count": "6",
        "Published_At": "2020-05-28T12:29:34Z",
        "Video_Title": "Gott dein Arzt Teil VIII | God your physician Part VIII"
    },
    {
        "Channel_ID": "UC_-LsoQ-dQns_PFIZ89Wy-w",
        "Video_ID": "m7muaGrH9B0",
        "View_Count": "8",
        "Published_At": "2020-05-18T20:51:31Z",
        "Video_Title": "Gott dein Arzt Teil VII | God your physician Part VII"
    },
    {
        "Channel_ID": "UC_-LsoQ-dQns_PFIZ89Wy-w",
        "Video_ID": "YXhrfvseHHk",
        "View_Count": "24",
        "Published_At": "2020-05-18T19:57:34Z",
        "Video_Title": "Siegreiches Leben | Victorious Life"
    },
    {
        "Channel_ID": "UC_-LsoQ-dQns_PFIZ89Wy-w",
        "Video_ID": "GgdCUKZ9RnY",
        "View_Count": "6",
        "Published_At": "2020-05-16T12:54:12Z",
        "Video_Title": "Tatsachen der Erl\u00f6sung Teil I | Redemptive facts Part I"
    },
    {
        "Channel_ID": "UC_-LsoQ-dQns_PFIZ89Wy-w",
        "Video_ID": "ZvKszoBvAvw",
        "View_Count": "3",
        "Published_At": "2020-05-16T12:28:59Z",
        "Video_Title": "Tatsachen der Erl\u00f6sung Teil II-2 | Redemptive facts Part II-2"
    },
    {
        "Channel_ID": "UC_-LsoQ-dQns_PFIZ89Wy-w",
        "Video_ID": "no9gDdfsa8Q",
        "View_Count": "6",
        "Published_At": "2020-05-16T12:07:21Z",
        "Video_Title": "Gott dein Arzt Teil VI | God your physician Part VI"
    },
    {
        "Channel_ID": "UC_-LsoQ-dQns_PFIZ89Wy-w",
        "Video_ID": "fhVDzBqbVtU",
        "View_Count": "6",
        "Published_At": "2020-05-16T11:10:43Z",
        "Video_Title": "Tatsachen der Erl\u00f6sung Teil II-1 | Redemptive facts Part II-1"
    },
    {
        "Channel_ID": "UC_-LsoQ-dQns_PFIZ89Wy-w",
        "Video_ID": "XssuuZSU34s",
        "View_Count": "4",
        "Published_At": "2020-05-16T10:38:22Z",
        "Video_Title": "Gott dein Arzt Teil V | God your physician Part V"
    },
    {
        "Channel_ID": "UC_-LsoQ-dQns_PFIZ89Wy-w",
        "Video_ID": "gJnVGLorEU0",
        "View_Count": "5",
        "Published_At": "2020-05-16T02:42:47Z",
        "Video_Title": "Gott dein Arzt Teil III | God your physician Part III"
    },
    {
        "Channel_ID": "UC_-LsoQ-dQns_PFIZ89Wy-w",
        "Video_ID": "MMaTaL91bMc",
        "View_Count": "11",
        "Published_At": "2020-05-16T02:39:19Z",
        "Video_Title": "Neues Leben | New Life"
    },
    {
        "Channel_ID": "UC_-LsoQ-dQns_PFIZ89Wy-w",
        "Video_ID": "oQHGQZX79zI",
        "View_Count": "6",
        "Published_At": "2020-05-16T02:33:00Z",
        "Video_Title": "CORONA Virus + Social Distancing = Neue M\u00f6glichkeiten"
    },
    {
        "Channel_ID": "UC_-LsoQ-dQns_PFIZ89Wy-w",
        "Video_ID": "_XFRyAE9WQA",
        "View_Count": "4",
        "Published_At": "2020-05-16T02:29:44Z",
        "Video_Title": "Gott dein Arzt Teil IV | God your physician Part IV"
    },
    {
        "Channel_ID": "UC_-LsoQ-dQns_PFIZ89Wy-w",
        "Video_ID": "tRbOO2BWFVU",
        "View_Count": "20",
        "Published_At": "2020-05-16T02:21:02Z",
        "Video_Title": "\u00dcberwinde Angst und Furcht | Overcome fear and anxiety"
    },
    {
        "Channel_ID": "UC_-LsoQ-dQns_PFIZ89Wy-w",
        "Video_ID": "ZT9NkfYTWng",
        "View_Count": "9",
        "Published_At": "2020-05-16T02:17:22Z",
        "Video_Title": "ER hat ein f\u00fcr alle Mal bezahlt | HE has paid once and for all"
    },
    {
        "Channel_ID": "UC_-LsoQ-dQns_PFIZ89Wy-w",
        "Video_ID": "OhPBBbo0ShE",
        "View_Count": "2",
        "Published_At": "2020-05-16T00:32:09Z",
        "Video_Title": "Gott dein Arzt Teil II | God your physician Part II"
    },
    {
        "Channel_ID": "UC_-LsoQ-dQns_PFIZ89Wy-w",
        "Video_ID": "iM_8jBN1i4M",
        "View_Count": "12",
        "Published_At": "2020-05-15T22:46:39Z",
        "Video_Title": "Halte an Gottes Wort fest | Hold on to God's Word"
    },
    {
        "Channel_ID": "UC_-LsoQ-dQns_PFIZ89Wy-w",
        "Video_ID": "TRa6LE3D7-E",
        "View_Count": "8",
        "Published_At": "2020-05-15T22:07:09Z",
        "Video_Title": "Gott dein Arzt Teil I // God your physician Part I"
    },
    {
        "Channel_ID": "UC_-LsoQ-dQns_PFIZ89Wy-w",
        "Video_ID": "SHYlBv22EJk",
        "View_Count": "14",
        "Published_At": "2020-05-15T20:47:37Z",
        "Video_Title": "Die souver\u00e4ne Macht Gottes und seine Gegenwart I God sovereign power and His presence"
    },
    {
        "Channel_ID": "UC_-LsoQ-dQns_PFIZ89Wy-w",
        "Video_ID": "knv1vOLLYwM",
        "View_Count": "42",
        "Published_At": "2020-03-24T20:04:00Z",
        "Video_Title": "Hab Keine Angst | Do Not Be Afraid"
    }
]