[
    {
        "Channel_ID": "UCmer0iGUyA-G9aNAOeBPZDg",
        "Video_ID": "LJfJdsmuUJQ",
        "View_Count": "184",
        "Published_At": "2024-07-21T22:08:20Z",
        "Video_Title": "Gott hat eine Bestimmung f\u00fcr dich! I    I  Predigt: Anil Nethala"
    },
    {
        "Channel_ID": "UCmer0iGUyA-G9aNAOeBPZDg",
        "Video_ID": "Mm9LnJQz3iU",
        "View_Count": "102",
        "Published_At": "2024-06-30T21:59:42Z",
        "Video_Title": "Rassismus vs. Vielfalt I    I  Predigt: Manuel Hintzen"
    },
    {
        "Channel_ID": "UCmer0iGUyA-G9aNAOeBPZDg",
        "Video_ID": "mAr2LmxhMgk",
        "View_Count": "70",
        "Published_At": "2024-06-16T21:47:12Z",
        "Video_Title": "Behind the scenes  I    I  Predigt: Christian Bongartz"
    },
    {
        "Channel_ID": "UCmer0iGUyA-G9aNAOeBPZDg",
        "Video_ID": "xMRz6MliXOQ",
        "View_Count": "99",
        "Published_At": "2024-06-09T22:03:27Z",
        "Video_Title": "Teamgeist  I  Gal.5,22  I  Predigt: Manuel Hintzen"
    },
    {
        "Channel_ID": "UCmer0iGUyA-G9aNAOeBPZDg",
        "Video_ID": "t933D8REAfU",
        "View_Count": "120",
        "Published_At": "2024-06-02T21:16:08Z",
        "Video_Title": "Heimspiel ist, wo du geliebt wirst  I  Predigt: Manuel Hintzen"
    },
    {
        "Channel_ID": "UCmer0iGUyA-G9aNAOeBPZDg",
        "Video_ID": "Epau5g-VPTU",
        "View_Count": "68",
        "Published_At": "2024-05-26T21:44:40Z",
        "Video_Title": "Erlebe den Heiligen Geist"
    },
    {
        "Channel_ID": "UCmer0iGUyA-G9aNAOeBPZDg",
        "Video_ID": "kA6sKvbkcoA",
        "View_Count": "61",
        "Published_At": "2024-05-19T21:44:15Z",
        "Video_Title": "Die Sch\u00f6nheit des Zerbrochenen"
    },
    {
        "Channel_ID": "UCmer0iGUyA-G9aNAOeBPZDg",
        "Video_ID": "o0Lo2JQtAS8",
        "View_Count": "75",
        "Published_At": "2024-05-12T22:12:38Z",
        "Video_Title": "Der Heilige Geist und deine Identit\u00e4t"
    },
    {
        "Channel_ID": "UCmer0iGUyA-G9aNAOeBPZDg",
        "Video_ID": "AQle6-5ejv4",
        "View_Count": "57",
        "Published_At": "2024-05-05T22:13:14Z",
        "Video_Title": "Gottesdienst 05.05.2025"
    },
    {
        "Channel_ID": "UCmer0iGUyA-G9aNAOeBPZDg",
        "Video_ID": "FY0fYMOYA78",
        "View_Count": "96",
        "Published_At": "2024-04-28T22:22:04Z",
        "Video_Title": "Was du l\u00f6st str\u00f6mt ein, was du bindest schickst du weg."
    },
    {
        "Channel_ID": "UCmer0iGUyA-G9aNAOeBPZDg",
        "Video_ID": "eIkOE6rAoLk",
        "View_Count": "91",
        "Published_At": "2024-04-21T21:54:49Z",
        "Video_Title": "Warum handelt Gott nicht immer sofort?"
    },
    {
        "Channel_ID": "UCmer0iGUyA-G9aNAOeBPZDg",
        "Video_ID": "v4ICmrYzmQ8",
        "View_Count": "95",
        "Published_At": "2024-04-14T22:11:45Z",
        "Video_Title": "Darf Gott der K\u00f6nig deines Herzens sein?"
    },
    {
        "Channel_ID": "UCmer0iGUyA-G9aNAOeBPZDg",
        "Video_ID": "L9N2bSL-SPw",
        "View_Count": "126",
        "Published_At": "2024-04-07T22:07:28Z",
        "Video_Title": "Ich bin nur Gast auf Erden"
    },
    {
        "Channel_ID": "UCmer0iGUyA-G9aNAOeBPZDg",
        "Video_ID": "4kyEWWYaVbw",
        "View_Count": "238",
        "Published_At": "2024-03-03T18:32:26Z",
        "Video_Title": "Sensibel, gereizt und aggressiv. Wohin mit all unserer Wut?"
    },
    {
        "Channel_ID": "UCmer0iGUyA-G9aNAOeBPZDg",
        "Video_ID": "HaTYrbYFhjU",
        "View_Count": "126",
        "Published_At": "2024-02-25T22:54:37Z",
        "Video_Title": "Gl\u00fcckwunsch - Seligpreisungen"
    },
    {
        "Channel_ID": "UCmer0iGUyA-G9aNAOeBPZDg",
        "Video_ID": "Z3GP0S72RJw",
        "View_Count": "124",
        "Published_At": "2024-02-18T22:52:09Z",
        "Video_Title": "Kirche- bewegt von Gottes Gegenwart"
    },
    {
        "Channel_ID": "UCmer0iGUyA-G9aNAOeBPZDg",
        "Video_ID": "gJTio6aqQxA",
        "View_Count": "146",
        "Published_At": "2024-02-11T23:07:23Z",
        "Video_Title": "Eine Einf\u00fchrung in die Bergpredigt"
    },
    {
        "Channel_ID": "UCmer0iGUyA-G9aNAOeBPZDg",
        "Video_ID": "gz8w6ag63jQ",
        "View_Count": "80",
        "Published_At": "2024-02-04T22:53:45Z",
        "Video_Title": "Mutig glauben- furchtlos leben"
    },
    {
        "Channel_ID": "UCmer0iGUyA-G9aNAOeBPZDg",
        "Video_ID": "YRXAgFnbvuM",
        "View_Count": "142",
        "Published_At": "2024-01-28T23:04:16Z",
        "Video_Title": "Loslassen und leichter leben"
    },
    {
        "Channel_ID": "UCmer0iGUyA-G9aNAOeBPZDg",
        "Video_ID": "fdaQqnRr_wc",
        "View_Count": "81",
        "Published_At": "2024-01-21T22:43:40Z",
        "Video_Title": "Weil Gott uns ein neues \"Sein\" geschenkt hat"
    },
    {
        "Channel_ID": "UCmer0iGUyA-G9aNAOeBPZDg",
        "Video_ID": "hNB_GVZthfk",
        "View_Count": "81",
        "Published_At": "2024-01-14T22:55:06Z",
        "Video_Title": "Vision f\u00fcr Mission I AGW  I 14.01.2024"
    },
    {
        "Channel_ID": "UCmer0iGUyA-G9aNAOeBPZDg",
        "Video_ID": "UUVPHHdsy7c",
        "View_Count": "134",
        "Published_At": "2024-01-07T22:57:48Z",
        "Video_Title": "Weil Gott genau wei\u00df, welche Pl\u00e4ne er f\u00fcr uns hat"
    },
    {
        "Channel_ID": "UCmer0iGUyA-G9aNAOeBPZDg",
        "Video_ID": "F_xsN7O-Cxw",
        "View_Count": "184",
        "Published_At": "2023-12-25T04:38:34Z",
        "Video_Title": "\"The King is born\" Heiligabend mit Gospelchor"
    },
    {
        "Channel_ID": "UCmer0iGUyA-G9aNAOeBPZDg",
        "Video_ID": "uTXiF-bl0pQ",
        "View_Count": "199",
        "Published_At": "2023-12-10T23:15:27Z",
        "Video_Title": "Gottes Frieden finden in turbulenten Zeiten"
    },
    {
        "Channel_ID": "UCmer0iGUyA-G9aNAOeBPZDg",
        "Video_ID": "BxF3eMGgCAY",
        "View_Count": "168",
        "Published_At": "2023-12-03T23:08:04Z",
        "Video_Title": "Dankbarkeit - Ein wirksames Mittel gegen Sorgen I  03.12.2023"
    },
    {
        "Channel_ID": "UCmer0iGUyA-G9aNAOeBPZDg",
        "Video_ID": "VyCqyWcRjoA",
        "View_Count": "287",
        "Published_At": "2023-11-27T06:16:09Z",
        "Video_Title": "Predigt Pastor  Pierre Ngnangock"
    },
    {
        "Channel_ID": "UCmer0iGUyA-G9aNAOeBPZDg",
        "Video_ID": "o6kmroz1akc",
        "View_Count": "212",
        "Published_At": "2023-11-19T22:48:53Z",
        "Video_Title": "Das Geheimnis des \u00d6lbaums I  R\u00f6mer 9-11"
    },
    {
        "Channel_ID": "UCmer0iGUyA-G9aNAOeBPZDg",
        "Video_ID": "4q1cyQJclGw",
        "View_Count": "680",
        "Published_At": "2023-11-12T22:52:12Z",
        "Video_Title": "Endzeitliche Prophetie und die Zukunft Israels  I 12.11.2023"
    },
    {
        "Channel_ID": "UCmer0iGUyA-G9aNAOeBPZDg",
        "Video_ID": "dGiCd3tR2nc",
        "View_Count": "394",
        "Published_At": "2023-11-05T22:57:58Z",
        "Video_Title": "Hat Gott Schluss gemacht mit Israel?  I 05.11.2023"
    },
    {
        "Channel_ID": "UCmer0iGUyA-G9aNAOeBPZDg",
        "Video_ID": "unTEdfhKhQk",
        "View_Count": "112",
        "Published_At": "2023-10-29T22:48:51Z",
        "Video_Title": "Wie wir andere zu wahrer Gr\u00f6\u00dfe f\u00fchren I 29.10.2023"
    },
    {
        "Channel_ID": "UCmer0iGUyA-G9aNAOeBPZDg",
        "Video_ID": "NDCmhEGge1M",
        "View_Count": "850",
        "Published_At": "2023-10-22T21:29:50Z",
        "Video_Title": "Plant Gott mein Leben und welche Rolle spiele ich darin? I  22.10.2023"
    },
    {
        "Channel_ID": "UCmer0iGUyA-G9aNAOeBPZDg",
        "Video_ID": "LQUIl6MQVcM",
        "View_Count": "218",
        "Published_At": "2023-10-15T21:55:47Z",
        "Video_Title": "Das Buch Ruth  I  Teil 3 I Lass uns die Beziehung definieren"
    },
    {
        "Channel_ID": "UCmer0iGUyA-G9aNAOeBPZDg",
        "Video_ID": "jJGazGIu90M",
        "View_Count": "173",
        "Published_At": "2023-10-08T22:05:17Z",
        "Video_Title": "Das Buch Ruth I Teil 2 I Auf diese Dinge solltest du bei dem ersten Date achten"
    },
    {
        "Channel_ID": "UCmer0iGUyA-G9aNAOeBPZDg",
        "Video_ID": "n4X3ggbQzr4",
        "View_Count": "273",
        "Published_At": "2023-10-01T22:09:23Z",
        "Video_Title": "Das Buch Ruth I Teil 1 I  Wenn es an der Zeit ist zu gehen"
    },
    {
        "Channel_ID": "UCmer0iGUyA-G9aNAOeBPZDg",
        "Video_ID": "WeLVwEp9o3E",
        "View_Count": "142",
        "Published_At": "2023-09-24T22:43:57Z",
        "Video_Title": "Gospel Fire International I Peter Franz I 24.09.2023"
    },
    {
        "Channel_ID": "UCmer0iGUyA-G9aNAOeBPZDg",
        "Video_ID": "IwrYwdImhoA",
        "View_Count": "130",
        "Published_At": "2023-09-17T22:17:22Z",
        "Video_Title": "Jesus der Friedef\u00fcrst I 17.09.2023"
    },
    {
        "Channel_ID": "UCmer0iGUyA-G9aNAOeBPZDg",
        "Video_ID": "RktkGs1Nk4Y",
        "View_Count": "289",
        "Published_At": "2023-09-10T22:20:42Z",
        "Video_Title": "Halte an Gottes Zusagen fest, bis du sie siehst I 10.09.2023"
    },
    {
        "Channel_ID": "UCmer0iGUyA-G9aNAOeBPZDg",
        "Video_ID": "81oLnllSxzU",
        "View_Count": "136",
        "Published_At": "2023-09-03T22:05:49Z",
        "Video_Title": "Schiffbruch erleben 03.09.2023"
    },
    {
        "Channel_ID": "UCmer0iGUyA-G9aNAOeBPZDg",
        "Video_ID": "Nlh8ReLzMrY",
        "View_Count": "170",
        "Published_At": "2023-08-27T21:59:02Z",
        "Video_Title": "Der Heilige Geist und unser Gehorsam I 27.08.2023"
    },
    {
        "Channel_ID": "UCmer0iGUyA-G9aNAOeBPZDg",
        "Video_ID": "SKoouzAzExw",
        "View_Count": "317",
        "Published_At": "2023-08-20T22:07:33Z",
        "Video_Title": "H\u00e4tte ich mich auch bekehrt, wenn mir das einer gesagt h\u00e4tte? I 20.08.2023"
    },
    {
        "Channel_ID": "UCmer0iGUyA-G9aNAOeBPZDg",
        "Video_ID": "WFE4o_eVxFI",
        "View_Count": "155",
        "Published_At": "2023-08-13T21:55:26Z",
        "Video_Title": "Das Reich Gottes ist Gerechtigkeit I 13.08.2023"
    },
    {
        "Channel_ID": "UCmer0iGUyA-G9aNAOeBPZDg",
        "Video_ID": "eFEWKvXb_Cg",
        "View_Count": "154",
        "Published_At": "2023-08-06T22:04:16Z",
        "Video_Title": "Die geheimnisvolle Kraft von Gottes Wort I 06.08.2023"
    },
    {
        "Channel_ID": "UCmer0iGUyA-G9aNAOeBPZDg",
        "Video_ID": "AdRbnR87Eoo",
        "View_Count": "110",
        "Published_At": "2023-07-30T22:09:15Z",
        "Video_Title": "Gottesdienst I 30.07.2023"
    },
    {
        "Channel_ID": "UCmer0iGUyA-G9aNAOeBPZDg",
        "Video_ID": "vVYNIbgj-S8",
        "View_Count": "621",
        "Published_At": "2023-07-23T22:32:30Z",
        "Video_Title": "Ist das Gott oder bin ich das? I 23.07.2023"
    },
    {
        "Channel_ID": "UCmer0iGUyA-G9aNAOeBPZDg",
        "Video_ID": "BoTce48NF4w",
        "View_Count": "110",
        "Published_At": "2023-07-16T22:00:27Z",
        "Video_Title": "Christ sein: Religion oder Beziehung I 16.07.2023"
    },
    {
        "Channel_ID": "UCmer0iGUyA-G9aNAOeBPZDg",
        "Video_ID": "052K3DaWxho",
        "View_Count": "104",
        "Published_At": "2023-07-09T21:52:19Z",
        "Video_Title": "Charakteristiken des Reiches Gottes I 09.07.2023"
    },
    {
        "Channel_ID": "UCmer0iGUyA-G9aNAOeBPZDg",
        "Video_ID": "RjzCvRHvIC0",
        "View_Count": "174",
        "Published_At": "2023-07-02T21:43:10Z",
        "Video_Title": "Gott macht alles neu I Tauf- Gottesdienst I 02.07.2023"
    },
    {
        "Channel_ID": "UCmer0iGUyA-G9aNAOeBPZDg",
        "Video_ID": "Yh_cImeVmxk",
        "View_Count": "111",
        "Published_At": "2023-06-25T22:15:25Z",
        "Video_Title": "Eine Kultur des positiven Redens in der Familie entwickeln I Michael Kienapfel I 25.06.2023"
    },
    {
        "Channel_ID": "UCmer0iGUyA-G9aNAOeBPZDg",
        "Video_ID": "uYwmDeen2os",
        "View_Count": "190",
        "Published_At": "2023-06-11T21:39:12Z",
        "Video_Title": "Gewinne den Kampf der Gedanken I 11.06.2023"
    },
    {
        "Channel_ID": "UCmer0iGUyA-G9aNAOeBPZDg",
        "Video_ID": "ygIUR24koy0",
        "View_Count": "119",
        "Published_At": "2023-06-04T22:21:39Z",
        "Video_Title": "Keine Furcht vor den Auswirkungen des Heiligen Geistes I 04.06.2023"
    },
    {
        "Channel_ID": "UCmer0iGUyA-G9aNAOeBPZDg",
        "Video_ID": "lWy7sEoCUDA",
        "View_Count": "178",
        "Published_At": "2023-05-28T22:12:55Z",
        "Video_Title": "Die Taufe im Heiligen Geist I 28.05.2023"
    },
    {
        "Channel_ID": "UCmer0iGUyA-G9aNAOeBPZDg",
        "Video_ID": "VjOdKtjATNA",
        "View_Count": "105",
        "Published_At": "2023-05-21T22:06:30Z",
        "Video_Title": "Der Heilige Geist als Geschenk Gottes"
    },
    {
        "Channel_ID": "UCmer0iGUyA-G9aNAOeBPZDg",
        "Video_ID": "ymD4TAuJIiE",
        "View_Count": "145",
        "Published_At": "2023-05-14T22:24:51Z",
        "Video_Title": "Sei anders, aber nicht komisch I Bastian Decker"
    },
    {
        "Channel_ID": "UCmer0iGUyA-G9aNAOeBPZDg",
        "Video_ID": "a4d-OTGgqfo",
        "View_Count": "169",
        "Published_At": "2023-05-07T22:08:01Z",
        "Video_Title": "Taufe- eine bewusste Entscheidung"
    },
    {
        "Channel_ID": "UCmer0iGUyA-G9aNAOeBPZDg",
        "Video_ID": "aLv741X5tMQ",
        "View_Count": "190",
        "Published_At": "2023-04-23T22:30:26Z",
        "Video_Title": "Frei werden durch Vergebung"
    },
    {
        "Channel_ID": "UCmer0iGUyA-G9aNAOeBPZDg",
        "Video_ID": "rtj9fyvb1Bc",
        "View_Count": "121",
        "Published_At": "2023-04-16T21:39:58Z",
        "Video_Title": "Blindfische k\u00f6nnen auch sehen lernen"
    },
    {
        "Channel_ID": "UCmer0iGUyA-G9aNAOeBPZDg",
        "Video_ID": "-IWDWJREGhk",
        "View_Count": "141",
        "Published_At": "2023-04-09T21:37:03Z",
        "Video_Title": "Die gro\u00dfen Dinge des Lebens erhalten wir nur geschenkt"
    },
    {
        "Channel_ID": "UCmer0iGUyA-G9aNAOeBPZDg",
        "Video_ID": "vpvALEYjBIc",
        "View_Count": "190",
        "Published_At": "2023-04-02T22:10:31Z",
        "Video_Title": "Gott gab uns eine zweite Chance  I  Manuel Hintzen"
    },
    {
        "Channel_ID": "UCmer0iGUyA-G9aNAOeBPZDg",
        "Video_ID": "ut3d8qlK9_k",
        "View_Count": "115",
        "Published_At": "2023-03-26T22:11:20Z",
        "Video_Title": "Reifes Leben I Manuel Hintzen"
    },
    {
        "Channel_ID": "UCmer0iGUyA-G9aNAOeBPZDg",
        "Video_ID": "VqgN11Vs_WM",
        "View_Count": "122",
        "Published_At": "2023-03-20T00:06:39Z",
        "Video_Title": "Wegweiser I Christian Bongartz"
    },
    {
        "Channel_ID": "UCmer0iGUyA-G9aNAOeBPZDg",
        "Video_ID": "vL6jphBvfaM",
        "View_Count": "131",
        "Published_At": "2023-03-12T23:40:31Z",
        "Video_Title": "Bestimmung I Manuel Hintzen"
    },
    {
        "Channel_ID": "UCmer0iGUyA-G9aNAOeBPZDg",
        "Video_ID": "BpyFhg34sk8",
        "View_Count": "159",
        "Published_At": "2023-03-05T23:04:58Z",
        "Video_Title": "W\u00fcrde I Manuel Hintzen"
    },
    {
        "Channel_ID": "UCmer0iGUyA-G9aNAOeBPZDg",
        "Video_ID": "BFZUQm98SRI",
        "View_Count": "164",
        "Published_At": "2023-02-26T22:55:57Z",
        "Video_Title": "Verbundenheit  I Manuel Hintzen"
    },
    {
        "Channel_ID": "UCmer0iGUyA-G9aNAOeBPZDg",
        "Video_ID": "bY8XJC5rBdU",
        "View_Count": "195",
        "Published_At": "2023-02-19T23:04:41Z",
        "Video_Title": "Lieben wenn es weh tut I Kevin Hintzen"
    },
    {
        "Channel_ID": "UCmer0iGUyA-G9aNAOeBPZDg",
        "Video_ID": "ze-BN5AFCaA",
        "View_Count": "160",
        "Published_At": "2023-02-12T22:59:28Z",
        "Video_Title": "Umarme was du has(s)t I Manuel Hintzen"
    },
    {
        "Channel_ID": "UCmer0iGUyA-G9aNAOeBPZDg",
        "Video_ID": "egXtX2gDRjs",
        "View_Count": "178",
        "Published_At": "2023-02-05T23:13:19Z",
        "Video_Title": "Wie du Jesus in der  Stille begegnest I Manuel Hintzen"
    },
    {
        "Channel_ID": "UCmer0iGUyA-G9aNAOeBPZDg",
        "Video_ID": "pgoFB6HWSAI",
        "View_Count": "123",
        "Published_At": "2023-01-29T23:23:31Z",
        "Video_Title": "Ber\u00fchre Eden I Manuel Hintzen"
    },
    {
        "Channel_ID": "UCmer0iGUyA-G9aNAOeBPZDg",
        "Video_ID": "WewT-yICl7A",
        "View_Count": "166",
        "Published_At": "2023-01-23T00:29:04Z",
        "Video_Title": "Gottes Sehnsucht nach dir I Manuel Hintzen"
    },
    {
        "Channel_ID": "UCmer0iGUyA-G9aNAOeBPZDg",
        "Video_ID": "d59hHpK0N7g",
        "View_Count": "140",
        "Published_At": "2023-01-15T22:53:35Z",
        "Video_Title": "Ge\u00f6ffnete H\u00e4nde I Manuel Hintzen"
    },
    {
        "Channel_ID": "UCmer0iGUyA-G9aNAOeBPZDg",
        "Video_ID": "1zAn29gHGqE",
        "View_Count": "90",
        "Published_At": "2023-01-08T22:47:59Z",
        "Video_Title": "Auftakt Allianz- Gebetswoche I 08.01.2023"
    },
    {
        "Channel_ID": "UCmer0iGUyA-G9aNAOeBPZDg",
        "Video_ID": "YBog09PfGKI",
        "View_Count": "144",
        "Published_At": "2022-12-25T04:07:12Z",
        "Video_Title": "Gott kommt zu dir"
    },
    {
        "Channel_ID": "UCmer0iGUyA-G9aNAOeBPZDg",
        "Video_ID": "vUv3ek-_TtQ",
        "View_Count": "162",
        "Published_At": "2022-12-18T13:29:39Z",
        "Video_Title": "...in seinem Wort und in seinem Geist"
    },
    {
        "Channel_ID": "UCmer0iGUyA-G9aNAOeBPZDg",
        "Video_ID": "HDQRTzAIPdo",
        "View_Count": "110",
        "Published_At": "2022-12-11T23:10:09Z",
        "Video_Title": "Gott sieht dein Leid"
    },
    {
        "Channel_ID": "UCmer0iGUyA-G9aNAOeBPZDg",
        "Video_ID": "Dr_r257bomc",
        "View_Count": "156",
        "Published_At": "2022-12-04T22:45:30Z",
        "Video_Title": "Leben in Gottes Gegenwart"
    },
    {
        "Channel_ID": "UCmer0iGUyA-G9aNAOeBPZDg",
        "Video_ID": "bGgxWmZF4B8",
        "View_Count": "223",
        "Published_At": "2022-11-27T23:12:39Z",
        "Video_Title": "Gottesdienst am 27.11.2022"
    },
    {
        "Channel_ID": "UCmer0iGUyA-G9aNAOeBPZDg",
        "Video_ID": "kgnt-DlY6xY",
        "View_Count": "118",
        "Published_At": "2022-11-20T23:23:51Z",
        "Video_Title": "Gottesdienst am 20.11.2022"
    },
    {
        "Channel_ID": "UCmer0iGUyA-G9aNAOeBPZDg",
        "Video_ID": "mpHbQfTFhtg",
        "View_Count": "108",
        "Published_At": "2022-11-13T23:15:39Z",
        "Video_Title": "Grenzen \u00fcberwinden"
    },
    {
        "Channel_ID": "UCmer0iGUyA-G9aNAOeBPZDg",
        "Video_ID": "DhqZuTZnIOg",
        "View_Count": "109",
        "Published_At": "2022-11-06T23:06:42Z",
        "Video_Title": "Gottes Feuer f\u00e4llt auf Hingabe"
    },
    {
        "Channel_ID": "UCmer0iGUyA-G9aNAOeBPZDg",
        "Video_ID": "MgRZ1tj1rv4",
        "View_Count": "300",
        "Published_At": "2022-10-30T23:09:24Z",
        "Video_Title": "Gott erh\u00f6rt dein Gebet I  30.10.2022"
    },
    {
        "Channel_ID": "UCmer0iGUyA-G9aNAOeBPZDg",
        "Video_ID": "q-f-RvS5kEI",
        "View_Count": "150",
        "Published_At": "2022-10-23T22:14:46Z",
        "Video_Title": "\"Die Kraft deiner Vision\""
    },
    {
        "Channel_ID": "UCmer0iGUyA-G9aNAOeBPZDg",
        "Video_ID": "6Sa7SSpxtcI",
        "View_Count": "250",
        "Published_At": "2022-10-16T21:55:26Z",
        "Video_Title": "\"Identit\u00e4t\" I  16.10.2022"
    },
    {
        "Channel_ID": "UCmer0iGUyA-G9aNAOeBPZDg",
        "Video_ID": "bYGyOHSABpY",
        "View_Count": "110",
        "Published_At": "2022-10-09T22:16:01Z",
        "Video_Title": "Gottesdienst I  09.10.2022 I EL SHADDAI"
    },
    {
        "Channel_ID": "UCmer0iGUyA-G9aNAOeBPZDg",
        "Video_ID": "0G9EHG2Eabw",
        "View_Count": "121",
        "Published_At": "2022-10-02T22:00:35Z",
        "Video_Title": "...freut sich auf die Wiederkunft Jesu"
    },
    {
        "Channel_ID": "UCmer0iGUyA-G9aNAOeBPZDg",
        "Video_ID": "QTTPjn_g3Co",
        "View_Count": "101",
        "Published_At": "2022-09-25T22:20:26Z",
        "Video_Title": "...lebt ein heiliges Leben"
    },
    {
        "Channel_ID": "UCmer0iGUyA-G9aNAOeBPZDg",
        "Video_ID": "SR7NnFYVW6U",
        "View_Count": "108",
        "Published_At": "2022-09-18T22:01:31Z",
        "Video_Title": "...setzt den richtigen \"Fokus\""
    },
    {
        "Channel_ID": "UCmer0iGUyA-G9aNAOeBPZDg",
        "Video_ID": "pPTl_Z7nR6U",
        "View_Count": "127",
        "Published_At": "2022-09-11T22:01:57Z",
        "Video_Title": "... besitzt ein \"warum\"  I  11.09.2022"
    },
    {
        "Channel_ID": "UCmer0iGUyA-G9aNAOeBPZDg",
        "Video_ID": "T9m6VD8C_N0",
        "View_Count": "95",
        "Published_At": "2022-07-31T21:41:10Z",
        "Video_Title": "Gottesfurcht Teil 4  I    I  31.07.2022"
    },
    {
        "Channel_ID": "UCmer0iGUyA-G9aNAOeBPZDg",
        "Video_ID": "-hIjkRblUg4",
        "View_Count": "90",
        "Published_At": "2022-07-24T21:54:57Z",
        "Video_Title": "Gottesfurcht Teil 3  I  Das B\u00f6se lassen und das Gute tun  I  24.07.2022"
    },
    {
        "Channel_ID": "UCmer0iGUyA-G9aNAOeBPZDg",
        "Video_ID": "KEtXojxjIOw",
        "View_Count": "305",
        "Published_At": "2022-07-18T11:12:35Z",
        "Video_Title": "Gottesfurcht Teil 2  I  Den Kurs korrigieren I 17.07.2022"
    },
    {
        "Channel_ID": "UCmer0iGUyA-G9aNAOeBPZDg",
        "Video_ID": "UeR7HCpUHCY",
        "View_Count": "547",
        "Published_At": "2022-07-10T15:55:03Z",
        "Video_Title": "Gottesfurcht Teil 1 I Bist du high? I  10.07.2022"
    },
    {
        "Channel_ID": "UCmer0iGUyA-G9aNAOeBPZDg",
        "Video_ID": "jr3aBAFMx_c",
        "View_Count": "368",
        "Published_At": "2022-07-03T21:49:22Z",
        "Video_Title": "Geistesgaben Teil 6 -I Zeichen und Wunder heute erleben"
    },
    {
        "Channel_ID": "UCmer0iGUyA-G9aNAOeBPZDg",
        "Video_ID": "0UR-fiBxUQw",
        "View_Count": "333",
        "Published_At": "2022-06-26T21:57:45Z",
        "Video_Title": "Under Pressure - Unter Druck weitergehen"
    },
    {
        "Channel_ID": "UCmer0iGUyA-G9aNAOeBPZDg",
        "Video_ID": "x96s5SLl8ak",
        "View_Count": "272",
        "Published_At": "2022-06-12T21:33:36Z",
        "Video_Title": "Geistesgaben Teil 4 I Vollmacht"
    },
    {
        "Channel_ID": "UCmer0iGUyA-G9aNAOeBPZDg",
        "Video_ID": "eEHUe8fkotU",
        "View_Count": "345",
        "Published_At": "2022-06-05T22:02:39Z",
        "Video_Title": "Die Geistesgaben - Weisheit und Erkenntnis"
    },
    {
        "Channel_ID": "UCmer0iGUyA-G9aNAOeBPZDg",
        "Video_ID": "mFJl3ts07PI",
        "View_Count": "458",
        "Published_At": "2022-05-29T22:12:03Z",
        "Video_Title": "Die Geistesgaben - Die Gabe des Glaubens"
    },
    {
        "Channel_ID": "UCmer0iGUyA-G9aNAOeBPZDg",
        "Video_ID": "3XB6ONZIpIM",
        "View_Count": "384",
        "Published_At": "2022-05-22T20:26:50Z",
        "Video_Title": "Die Geistesgaben- Einf\u00fchrung"
    },
    {
        "Channel_ID": "UCmer0iGUyA-G9aNAOeBPZDg",
        "Video_ID": "TyzK4n0Uiv4",
        "View_Count": "443",
        "Published_At": "2022-05-08T22:10:28Z",
        "Video_Title": "Der Weinstock und die Reben  I  Pastor Manuel Hintzen"
    },
    {
        "Channel_ID": "UCmer0iGUyA-G9aNAOeBPZDg",
        "Video_ID": "zgheYTFa8tE",
        "View_Count": "414",
        "Published_At": "2022-05-01T22:27:03Z",
        "Video_Title": "Licht in der Finsternis  I  Pastor Manuel Hintzen"
    },
    {
        "Channel_ID": "UCmer0iGUyA-G9aNAOeBPZDg",
        "Video_ID": "Pxs_6boIJjQ",
        "View_Count": "495",
        "Published_At": "2022-04-24T21:44:36Z",
        "Video_Title": "Der gute Hirte  I  Robin Dittrich"
    },
    {
        "Channel_ID": "UCmer0iGUyA-G9aNAOeBPZDg",
        "Video_ID": "EDXT3-d4gQ4",
        "View_Count": "446",
        "Published_At": "2022-04-17T21:48:08Z",
        "Video_Title": "Der Weg, die Wahrheit und das Leben  I  Pastor Manuel Hintzen"
    },
    {
        "Channel_ID": "UCmer0iGUyA-G9aNAOeBPZDg",
        "Video_ID": "mxt3FaltHH0",
        "View_Count": "427",
        "Published_At": "2022-04-10T22:00:22Z",
        "Video_Title": "H\u00f6r hin und lass dich leiten I Dominik Nachtrieb I  10.04.2022"
    },
    {
        "Channel_ID": "UCmer0iGUyA-G9aNAOeBPZDg",
        "Video_ID": "_lAXzr7Wijo",
        "View_Count": "353",
        "Published_At": "2022-04-03T22:05:31Z",
        "Video_Title": "Wie dein Glaube im Alltag sein Feuer beh\u00e4lt / Pastor Manuel Hintzen / 03.04.2022"
    },
    {
        "Channel_ID": "UCmer0iGUyA-G9aNAOeBPZDg",
        "Video_ID": "cgmBlUjX6gw",
        "View_Count": "309",
        "Published_At": "2022-03-27T22:00:50Z",
        "Video_Title": "Stark ihn st\u00fcrmischen Zeiten / Pastor Manuel Hintzen / 27.03.2022"
    },
    {
        "Channel_ID": "UCmer0iGUyA-G9aNAOeBPZDg",
        "Video_ID": "hHmLV5zTBk4",
        "View_Count": "562",
        "Published_At": "2022-03-20T23:29:54Z",
        "Video_Title": "Vom gelassenen Umgang mit der Endzeit / Pastor Manuel Hintzen / 20.03.2022"
    },
    {
        "Channel_ID": "UCmer0iGUyA-G9aNAOeBPZDg",
        "Video_ID": "pWmOeMF-ENQ",
        "View_Count": "399",
        "Published_At": "2022-03-13T22:35:58Z",
        "Video_Title": "Im Feuer stehen  //  13.03.2022"
    },
    {
        "Channel_ID": "UCmer0iGUyA-G9aNAOeBPZDg",
        "Video_ID": "0ETf3oipgrE",
        "View_Count": "383",
        "Published_At": "2022-03-06T22:59:33Z",
        "Video_Title": "Ein herausragender Lebensstil  //  06.03.2022"
    },
    {
        "Channel_ID": "UCmer0iGUyA-G9aNAOeBPZDg",
        "Video_ID": "dc6kEcAL6YM",
        "View_Count": "134",
        "Published_At": "2022-02-27T23:14:04Z",
        "Video_Title": "Freundschaft mit Gott  //  27.02.2022"
    },
    {
        "Channel_ID": "UCmer0iGUyA-G9aNAOeBPZDg",
        "Video_ID": "BkdvJmj241c",
        "View_Count": "454",
        "Published_At": "2022-02-20T23:02:01Z",
        "Video_Title": "Alles paletti? Von der Sch\u00f6nheit des Scheiterns"
    },
    {
        "Channel_ID": "UCmer0iGUyA-G9aNAOeBPZDg",
        "Video_ID": "0X4v_VoFAxA",
        "View_Count": "116",
        "Published_At": "2022-02-13T22:51:15Z",
        "Video_Title": "Frag immer erst \"warum\" Visions Sonntag"
    },
    {
        "Channel_ID": "UCmer0iGUyA-G9aNAOeBPZDg",
        "Video_ID": "gmfpUQNPGl8",
        "View_Count": "572",
        "Published_At": "2022-02-06T14:13:11Z",
        "Video_Title": "Ein guter Grund deine Gewohnheiten zu \u00fcberdenken Teil 4"
    },
    {
        "Channel_ID": "UCmer0iGUyA-G9aNAOeBPZDg",
        "Video_ID": "NPLN5AFMb7E",
        "View_Count": "462",
        "Published_At": "2022-01-30T16:39:23Z",
        "Video_Title": "\"Der Einfluss meiner Worte\" Teil 3"
    },
    {
        "Channel_ID": "UCmer0iGUyA-G9aNAOeBPZDg",
        "Video_ID": "ORstwpeP-es",
        "View_Count": "457",
        "Published_At": "2022-01-23T17:56:50Z",
        "Video_Title": "\"Du darfst nicht alles glauben was du denkst\" Teil 2"
    },
    {
        "Channel_ID": "UCmer0iGUyA-G9aNAOeBPZDg",
        "Video_ID": "R92zYVSSSEY",
        "View_Count": "445",
        "Published_At": "2022-01-16T22:52:56Z",
        "Video_Title": "\"Tr\u00e4ume gro\u00df &  starte klein\" Teil 1"
    },
    {
        "Channel_ID": "UCmer0iGUyA-G9aNAOeBPZDg",
        "Video_ID": "jbbD0vT753Y",
        "View_Count": "217",
        "Published_At": "2021-12-25T04:20:31Z",
        "Video_Title": "Heiligabend Gottesdienst 2021"
    },
    {
        "Channel_ID": "UCmer0iGUyA-G9aNAOeBPZDg",
        "Video_ID": "18in1Iwg6jQ",
        "View_Count": "205",
        "Published_At": "2021-12-19T22:46:57Z",
        "Video_Title": "Wie du die Kontrolle \u00fcber dein Leben zur\u00fcck gewinnst // 19.12.2021"
    },
    {
        "Channel_ID": "UCmer0iGUyA-G9aNAOeBPZDg",
        "Video_ID": "khM99ly6m5s",
        "View_Count": "1447",
        "Published_At": "2021-12-12T15:24:19Z",
        "Video_Title": "Deine besten Tage sind jetzt // 12.12.2021"
    },
    {
        "Channel_ID": "UCmer0iGUyA-G9aNAOeBPZDg",
        "Video_ID": "csFYDTWAvw0",
        "View_Count": "124",
        "Published_At": "2021-12-05T23:01:09Z",
        "Video_Title": "Immer funktionieren funktioniert halt nicht // 05.12.2021"
    },
    {
        "Channel_ID": "UCmer0iGUyA-G9aNAOeBPZDg",
        "Video_ID": "nqcibb4Bi2s",
        "View_Count": "133",
        "Published_At": "2021-11-28T22:57:35Z",
        "Video_Title": "Du musst nicht an deinen eigenen Glauben glauben  // 28.11.2021"
    },
    {
        "Channel_ID": "UCmer0iGUyA-G9aNAOeBPZDg",
        "Video_ID": "aBRXWO-XjJQ",
        "View_Count": "94",
        "Published_At": "2021-11-21T22:56:58Z",
        "Video_Title": "Warum r\u00fcckt Gott mir auf die Pelle?  // 21.11.2021"
    },
    {
        "Channel_ID": "UCmer0iGUyA-G9aNAOeBPZDg",
        "Video_ID": "sigH08-ZWR8",
        "View_Count": "102",
        "Published_At": "2021-11-14T22:50:24Z",
        "Video_Title": "Wer braucht eigentlich noch die Kirche?  // 14.11.2021"
    },
    {
        "Channel_ID": "UCmer0iGUyA-G9aNAOeBPZDg",
        "Video_ID": "SS_fYO48DvU",
        "View_Count": "79",
        "Published_At": "2021-11-07T23:18:09Z",
        "Video_Title": "// Nat\u00fcrlich? \u00dcbernat\u00fcrlich?Was hat das mit mir zu tun?  Konzerthaus 07.11.2021"
    },
    {
        "Channel_ID": "UCmer0iGUyA-G9aNAOeBPZDg",
        "Video_ID": "lG-uKfQESZ0",
        "View_Count": "139",
        "Published_At": "2021-10-31T22:51:33Z",
        "Video_Title": "Warum beten, wenn Gott sowieso einen Plan hat?  //  Konzerthaus 31.10.2021"
    },
    {
        "Channel_ID": "UCmer0iGUyA-G9aNAOeBPZDg",
        "Video_ID": "hTMGlBoqnxA",
        "View_Count": "167",
        "Published_At": "2021-10-24T21:30:59Z",
        "Video_Title": "Warum wir uns nicht sorgen m\u00fcssen // 24.10.2021"
    },
    {
        "Channel_ID": "UCmer0iGUyA-G9aNAOeBPZDg",
        "Video_ID": "kAVcuiCR4yM",
        "View_Count": "311",
        "Published_At": "2021-10-17T22:06:03Z",
        "Video_Title": "Befreiende Wahrheit // 17.10.2021"
    },
    {
        "Channel_ID": "UCmer0iGUyA-G9aNAOeBPZDg",
        "Video_ID": "52AMCmrNZMk",
        "View_Count": "142",
        "Published_At": "2021-10-03T22:09:48Z",
        "Video_Title": "Gottes Methode sind Menschen // 3.10.2021"
    },
    {
        "Channel_ID": "UCmer0iGUyA-G9aNAOeBPZDg",
        "Video_ID": "NXOrAayFsMs",
        "View_Count": "69",
        "Published_At": "2021-09-26T22:07:18Z",
        "Video_Title": "Jonas Reise und seine Hingabe // 26.09.2021"
    },
    {
        "Channel_ID": "UCmer0iGUyA-G9aNAOeBPZDg",
        "Video_ID": "HzeOetfIaWc",
        "View_Count": "83",
        "Published_At": "2021-09-19T21:58:33Z",
        "Video_Title": "Der neue Weg // 19.09.2021"
    },
    {
        "Channel_ID": "UCmer0iGUyA-G9aNAOeBPZDg",
        "Video_ID": "BG5602KP2B8",
        "View_Count": "456",
        "Published_At": "2021-09-12T22:14:01Z",
        "Video_Title": "Gott  wohnt im Lobpreis seine T\u00f6chter und S\u00f6hne // 12.09.2021"
    },
    {
        "Channel_ID": "UCmer0iGUyA-G9aNAOeBPZDg",
        "Video_ID": "5ZSsyDzbvic",
        "View_Count": "137",
        "Published_At": "2021-09-05T21:59:17Z",
        "Video_Title": "In deinem Gott bist du ein \u00dcberwinder // 05.09.2021"
    },
    {
        "Channel_ID": "UCmer0iGUyA-G9aNAOeBPZDg",
        "Video_ID": "ppT8MXwPIbI",
        "View_Count": "109",
        "Published_At": "2021-08-29T21:46:12Z",
        "Video_Title": "Gott schreibt auf krummen Zeilen gerade"
    },
    {
        "Channel_ID": "UCmer0iGUyA-G9aNAOeBPZDg",
        "Video_ID": "HDne5x8N_Kw",
        "View_Count": "319",
        "Published_At": "2021-08-15T21:55:36Z",
        "Video_Title": "J\u00fcrgen B\u00fchler - Israel"
    },
    {
        "Channel_ID": "UCmer0iGUyA-G9aNAOeBPZDg",
        "Video_ID": "-g5Hm5liPhw",
        "View_Count": "117",
        "Published_At": "2021-08-08T21:54:15Z",
        "Video_Title": "FES Heidenheim"
    },
    {
        "Channel_ID": "UCmer0iGUyA-G9aNAOeBPZDg",
        "Video_ID": "Wfn_-MoWf1c",
        "View_Count": "149",
        "Published_At": "2021-08-01T21:44:38Z",
        "Video_Title": "FES Heidenheim"
    },
    {
        "Channel_ID": "UCmer0iGUyA-G9aNAOeBPZDg",
        "Video_ID": "qIOOoMLQX3E",
        "View_Count": "110",
        "Published_At": "2021-07-25T22:21:59Z",
        "Video_Title": "Wenn Gottes Gegenwart in unser Leben einzieht- oder \"Wenn K\u00f6nige tanzen\""
    },
    {
        "Channel_ID": "UCmer0iGUyA-G9aNAOeBPZDg",
        "Video_ID": "jO37yoSQaic",
        "View_Count": "124",
        "Published_At": "2021-07-18T22:04:16Z",
        "Video_Title": "Willst du gesund werden?"
    },
    {
        "Channel_ID": "UCmer0iGUyA-G9aNAOeBPZDg",
        "Video_ID": "gWRDJd2Mpks",
        "View_Count": "103",
        "Published_At": "2021-07-11T22:08:12Z",
        "Video_Title": "Du & Ich \u2013 Den Bund gemeinsam halten- Gottesfurcht"
    },
    {
        "Channel_ID": "UCmer0iGUyA-G9aNAOeBPZDg",
        "Video_ID": "NjiHAhlJ-tI",
        "View_Count": "105",
        "Published_At": "2021-07-04T19:39:48Z",
        "Video_Title": "\"Du & Ich \u2013 Dem B\u00f6sen gemeinsam widerstehen\" // 04.07.2021"
    },
    {
        "Channel_ID": "UCmer0iGUyA-G9aNAOeBPZDg",
        "Video_ID": "5AtbOugidFc",
        "View_Count": "220",
        "Published_At": "2021-06-27T22:43:24Z",
        "Video_Title": "\"Du & Ich\" - Eine gemeinsame Mission\"  // 27.06.2021"
    },
    {
        "Channel_ID": "UCmer0iGUyA-G9aNAOeBPZDg",
        "Video_ID": "CdlVhmSFNPM",
        "View_Count": "99",
        "Published_At": "2021-06-20T22:24:50Z",
        "Video_Title": "\"Du & Ich\" -  Gott im Mittelpunkt  // 20.06.2021"
    },
    {
        "Channel_ID": "UCmer0iGUyA-G9aNAOeBPZDg",
        "Video_ID": "bPqYK6TvceY",
        "View_Count": "102",
        "Published_At": "2021-06-13T22:24:53Z",
        "Video_Title": "Hunger nach mehr von Gott  //13.06.2021"
    },
    {
        "Channel_ID": "UCmer0iGUyA-G9aNAOeBPZDg",
        "Video_ID": "mlYwx7WsdfE",
        "View_Count": "73",
        "Published_At": "2021-06-06T22:10:04Z",
        "Video_Title": "Das Wirken des Heiligen Geistes in der Geschichte - //06.06.2021"
    },
    {
        "Channel_ID": "UCmer0iGUyA-G9aNAOeBPZDg",
        "Video_ID": "tX2Bev0e4tk",
        "View_Count": "84",
        "Published_At": "2021-05-30T22:01:13Z",
        "Video_Title": "Livestream  - Apostelgeschichte Teil 3 //30.05.2021"
    },
    {
        "Channel_ID": "UCmer0iGUyA-G9aNAOeBPZDg",
        "Video_ID": "6ZHWjZF9bUg",
        "View_Count": "128",
        "Published_At": "2021-05-23T22:21:59Z",
        "Video_Title": "Wenn der Himmel die Erde ber\u00fchrt  - Apostelgeschichte Teil 2 //23.05.2021"
    },
    {
        "Channel_ID": "UCmer0iGUyA-G9aNAOeBPZDg",
        "Video_ID": "0l1tlmQVIQI",
        "View_Count": "206",
        "Published_At": "2021-05-16T22:19:38Z",
        "Video_Title": "Die Revolution des Himmels - Apostelgeschichte  //16.05.2021"
    },
    {
        "Channel_ID": "UCmer0iGUyA-G9aNAOeBPZDg",
        "Video_ID": "mSEYHTapekI",
        "View_Count": "147",
        "Published_At": "2021-05-09T22:11:25Z",
        "Video_Title": "Muttertag 2021 \"Du bist einzigartig\" //09.05.2021"
    },
    {
        "Channel_ID": "UCmer0iGUyA-G9aNAOeBPZDg",
        "Video_ID": "gmiLj3CLxJ8",
        "View_Count": "157",
        "Published_At": "2021-05-02T22:23:17Z",
        "Video_Title": "Wie du deine Sorgen entsorgen kannst //02.05.2021"
    },
    {
        "Channel_ID": "UCmer0iGUyA-G9aNAOeBPZDg",
        "Video_ID": "lthqRw7FBeI",
        "View_Count": "182",
        "Published_At": "2021-04-25T22:13:07Z",
        "Video_Title": "Liebe Deinen Alltag - Eine neue Sch\u00f6pfung  //25.04.2021"
    },
    {
        "Channel_ID": "UCmer0iGUyA-G9aNAOeBPZDg",
        "Video_ID": "o0pfdMrfnqs",
        "View_Count": "193",
        "Published_At": "2021-04-18T22:19:00Z",
        "Video_Title": "Heilig leben- In einer verr\u00fcckten Welt //18.04.2021"
    },
    {
        "Channel_ID": "UCmer0iGUyA-G9aNAOeBPZDg",
        "Video_ID": "lQZbBcxnquI",
        "View_Count": "202",
        "Published_At": "2021-04-11T22:13:45Z",
        "Video_Title": "Glaube, Liebe, Hoffnung in der Familie / 11.04.2021"
    },
    {
        "Channel_ID": "UCmer0iGUyA-G9aNAOeBPZDg",
        "Video_ID": "I6XTbvsJjK8",
        "View_Count": "180",
        "Published_At": "2021-04-04T22:11:15Z",
        "Video_Title": "Ostern - Gott in der Welt feiern // 04.04.2021"
    },
    {
        "Channel_ID": "UCmer0iGUyA-G9aNAOeBPZDg",
        "Video_ID": "dDnBjNi6wqI",
        "View_Count": "201",
        "Published_At": "2021-03-28T22:27:19Z",
        "Video_Title": "L(i)ebe Deinen Alltag  - Glaube beginnt bei dir // 28.03.2021"
    },
    {
        "Channel_ID": "UCmer0iGUyA-G9aNAOeBPZDg",
        "Video_ID": "WxKVdI-KkPY",
        "View_Count": "297",
        "Published_At": "2021-03-21T23:18:35Z",
        "Video_Title": "Wie wird es denn im Himmel sein?  // 21.03.2021"
    },
    {
        "Channel_ID": "UCmer0iGUyA-G9aNAOeBPZDg",
        "Video_ID": "lACrSiWC8k0",
        "View_Count": "306",
        "Published_At": "2021-03-14T23:12:20Z",
        "Video_Title": "Gottes Liebe und das Gericht. Wie passt das zusammen?  // 14.03.2021"
    },
    {
        "Channel_ID": "UCmer0iGUyA-G9aNAOeBPZDg",
        "Video_ID": "sdvN0467zQE",
        "View_Count": "605",
        "Published_At": "2021-03-07T23:14:12Z",
        "Video_Title": "Eine Minute nachdem Du stirbst  // 07.03.2021"
    },
    {
        "Channel_ID": "UCmer0iGUyA-G9aNAOeBPZDg",
        "Video_ID": "-ma0U0ri3XY",
        "View_Count": "198",
        "Published_At": "2021-02-28T23:15:44Z",
        "Video_Title": "Metamorphosis - Das neue Leben der Kinder Gottes // 28.02.2021"
    },
    {
        "Channel_ID": "UCmer0iGUyA-G9aNAOeBPZDg",
        "Video_ID": "aWg-wIQyk40",
        "View_Count": "162",
        "Published_At": "2021-02-21T23:20:06Z",
        "Video_Title": "Metamorphosis // Gott gestaltet durch Dich // 21.02.2021"
    },
    {
        "Channel_ID": "UCmer0iGUyA-G9aNAOeBPZDg",
        "Video_ID": "g0rhGh4qXFk",
        "View_Count": "155",
        "Published_At": "2021-02-14T23:16:13Z",
        "Video_Title": "Wie wir aus unseren Routinen ausbrechen k\u00f6nnen  // 14.02.2021"
    },
    {
        "Channel_ID": "UCmer0iGUyA-G9aNAOeBPZDg",
        "Video_ID": "oILPXD3uJtg",
        "View_Count": "154",
        "Published_At": "2021-02-07T23:11:55Z",
        "Video_Title": "Livestream  // 07.02.2021"
    },
    {
        "Channel_ID": "UCmer0iGUyA-G9aNAOeBPZDg",
        "Video_ID": "PExKbJ6zq_M",
        "View_Count": "174",
        "Published_At": "2021-01-31T23:26:28Z",
        "Video_Title": "Lifestyle // Sabbat // 31.01.2021"
    },
    {
        "Channel_ID": "UCmer0iGUyA-G9aNAOeBPZDg",
        "Video_ID": "pk5GBFTFYpY",
        "View_Count": "252",
        "Published_At": "2021-01-24T22:59:11Z",
        "Video_Title": "Lifestyle // Minimalismus // 24.01.2021"
    },
    {
        "Channel_ID": "UCmer0iGUyA-G9aNAOeBPZDg",
        "Video_ID": "PADlZBbIh80",
        "View_Count": "196",
        "Published_At": "2021-01-17T23:17:02Z",
        "Video_Title": "Lifestyle // Entschleunigung // 17.01.2021"
    },
    {
        "Channel_ID": "UCmer0iGUyA-G9aNAOeBPZDg",
        "Video_ID": "iyPDwxs6vKM",
        "View_Count": "108",
        "Published_At": "2021-01-10T22:51:28Z",
        "Video_Title": "Allianz Gebetswoche // Lebenselixier Bibel // 10.01.2021"
    },
    {
        "Channel_ID": "UCmer0iGUyA-G9aNAOeBPZDg",
        "Video_ID": "pbJzrReKhrc",
        "View_Count": "226",
        "Published_At": "2021-01-03T23:24:26Z",
        "Video_Title": "Lifestyle // STILLE // 03.01.2021"
    },
    {
        "Channel_ID": "UCmer0iGUyA-G9aNAOeBPZDg",
        "Video_ID": "Vs-GzY_374s",
        "View_Count": "500",
        "Published_At": "2020-12-24T14:00:27Z",
        "Video_Title": "Heilig Abend Gottesdienst 2020"
    },
    {
        "Channel_ID": "UCmer0iGUyA-G9aNAOeBPZDg",
        "Video_ID": "KjtugVMpj6g",
        "View_Count": "562",
        "Published_At": "2020-12-24T13:00:27Z",
        "Video_Title": "Krippenspiel 2020"
    },
    {
        "Channel_ID": "UCmer0iGUyA-G9aNAOeBPZDg",
        "Video_ID": "LLyFQDySCio",
        "View_Count": "145",
        "Published_At": "2020-12-21T14:47:28Z",
        "Video_Title": "Bastelanleitung Weihnachtsstern"
    },
    {
        "Channel_ID": "UCmer0iGUyA-G9aNAOeBPZDg",
        "Video_ID": "3m4qbUHlp04",
        "View_Count": "148",
        "Published_At": "2020-12-20T22:57:08Z",
        "Video_Title": "Ein Kind mit vielen Namen - Zoom Gottesdienst 20.12.2020"
    },
    {
        "Channel_ID": "UCmer0iGUyA-G9aNAOeBPZDg",
        "Video_ID": "tNa0ngfPyp0",
        "View_Count": "288",
        "Published_At": "2020-12-13T23:05:39Z",
        "Video_Title": "Was w\u00e4re wenn... \"Zuverl\u00e4ssigkeit\""
    },
    {
        "Channel_ID": "UCmer0iGUyA-G9aNAOeBPZDg",
        "Video_ID": "HmVNvqOnJ3o",
        "View_Count": "183",
        "Published_At": "2020-12-06T23:02:30Z",
        "Video_Title": "Was w\u00e4re wenn // Hilfsbereitschaft // 06.12.2020"
    },
    {
        "Channel_ID": "UCmer0iGUyA-G9aNAOeBPZDg",
        "Video_ID": "ni-j6xQqsLo",
        "View_Count": "188",
        "Published_At": "2020-11-29T23:22:41Z",
        "Video_Title": "Was w\u00e4re wenn // Leben entfalten // 29.11.2020"
    },
    {
        "Channel_ID": "UCmer0iGUyA-G9aNAOeBPZDg",
        "Video_ID": "grP9jj9vOQI",
        "View_Count": "155",
        "Published_At": "2020-11-22T12:49:23Z",
        "Video_Title": "Was w\u00e4re wenn // Wertsch\u00e4tzung // 22.11.2020"
    },
    {
        "Channel_ID": "UCmer0iGUyA-G9aNAOeBPZDg",
        "Video_ID": "M7EB35NuPaQ",
        "View_Count": "202",
        "Published_At": "2020-11-15T23:14:27Z",
        "Video_Title": "Was w\u00e4re wenn  //  Erwartung // 15.11.2020"
    },
    {
        "Channel_ID": "UCmer0iGUyA-G9aNAOeBPZDg",
        "Video_ID": "Yv_w7w_mt4Q",
        "View_Count": "229",
        "Published_At": "2020-11-08T23:17:35Z",
        "Video_Title": "Was w\u00e4re wenn  //  Gastfreundschaft  // 8.11.2020"
    },
    {
        "Channel_ID": "UCmer0iGUyA-G9aNAOeBPZDg",
        "Video_ID": "KKzotrMkzZ0",
        "View_Count": "296",
        "Published_At": "2020-11-01T23:27:12Z",
        "Video_Title": "Sorgen entsorgen und Frieden finden - 1.11.2020"
    },
    {
        "Channel_ID": "UCmer0iGUyA-G9aNAOeBPZDg",
        "Video_ID": "WduiGVrTCWw",
        "View_Count": "123",
        "Published_At": "2020-10-25T23:16:15Z",
        "Video_Title": "Starke Vorbilder -  25.10.2020"
    },
    {
        "Channel_ID": "UCmer0iGUyA-G9aNAOeBPZDg",
        "Video_ID": "hkyg-uKtKkI",
        "View_Count": "106",
        "Published_At": "2020-10-18T22:30:43Z",
        "Video_Title": "Gottesdienst  -  18.10.2020"
    },
    {
        "Channel_ID": "UCmer0iGUyA-G9aNAOeBPZDg",
        "Video_ID": "aqNvt417n6U",
        "View_Count": "143",
        "Published_At": "2020-10-11T22:08:09Z",
        "Video_Title": "Gottesdienst  -  11.10.2020"
    },
    {
        "Channel_ID": "UCmer0iGUyA-G9aNAOeBPZDg",
        "Video_ID": "ccHDBeu9_sU",
        "View_Count": "147",
        "Published_At": "2020-10-04T22:17:59Z",
        "Video_Title": "Orientierung bei Spannungen und Konflikten-   -  04.10.2020"
    },
    {
        "Channel_ID": "UCmer0iGUyA-G9aNAOeBPZDg",
        "Video_ID": "4IIy1o87_Ts",
        "View_Count": "304",
        "Published_At": "2020-09-27T22:40:23Z",
        "Video_Title": "MAUERERFAHRUNGEN -  27.09.2020"
    },
    {
        "Channel_ID": "UCmer0iGUyA-G9aNAOeBPZDg",
        "Video_ID": "fhZTP4ZmeZA",
        "View_Count": "210",
        "Published_At": "2020-09-20T22:26:12Z",
        "Video_Title": "Wie finde ich echten Frieden?  20.09.2020"
    },
    {
        "Channel_ID": "UCmer0iGUyA-G9aNAOeBPZDg",
        "Video_ID": "YaU24EfVsIA",
        "View_Count": "137",
        "Published_At": "2020-09-13T22:08:18Z",
        "Video_Title": "Gottesdienst  13.09.2020"
    },
    {
        "Channel_ID": "UCmer0iGUyA-G9aNAOeBPZDg",
        "Video_ID": "k_lheZbr5nE",
        "View_Count": "106",
        "Published_At": "2020-09-06T22:15:24Z",
        "Video_Title": "\"Get out of the box\" - Gottesdienst  06.09.2020"
    },
    {
        "Channel_ID": "UCmer0iGUyA-G9aNAOeBPZDg",
        "Video_ID": "O-BiABrXzXs",
        "View_Count": "150",
        "Published_At": "2020-08-30T22:20:27Z",
        "Video_Title": "\"SELA\" Gottesdienst  30.08.2020"
    },
    {
        "Channel_ID": "UCmer0iGUyA-G9aNAOeBPZDg",
        "Video_ID": "U30NkXF3Amc",
        "View_Count": "252",
        "Published_At": "2020-08-23T22:10:13Z",
        "Video_Title": "\"Was meinem Leben Richtung gibt\" Gottesdienst  23.08.2020"
    },
    {
        "Channel_ID": "UCmer0iGUyA-G9aNAOeBPZDg",
        "Video_ID": "1ogKt1w5w-0",
        "View_Count": "143",
        "Published_At": "2020-08-16T22:07:23Z",
        "Video_Title": "\"Neue Horizonte\" Gottesdienst  16.08.2020"
    },
    {
        "Channel_ID": "UCmer0iGUyA-G9aNAOeBPZDg",
        "Video_ID": "WJnbGiWGe5Q",
        "View_Count": "192",
        "Published_At": "2020-08-09T21:56:43Z",
        "Video_Title": "Gottesdienst  09.08.2020"
    },
    {
        "Channel_ID": "UCmer0iGUyA-G9aNAOeBPZDg",
        "Video_ID": "Hn-dT3ksTqI",
        "View_Count": "169",
        "Published_At": "2020-08-02T22:08:57Z",
        "Video_Title": "Gottesdienst  02.08.2020"
    },
    {
        "Channel_ID": "UCmer0iGUyA-G9aNAOeBPZDg",
        "Video_ID": "kX_8_D1xnG8",
        "View_Count": "85",
        "Published_At": "2020-07-26T21:57:55Z",
        "Video_Title": "Gottesdienst  26.07.2020"
    },
    {
        "Channel_ID": "UCmer0iGUyA-G9aNAOeBPZDg",
        "Video_ID": "n4TmpOKXv_A",
        "View_Count": "148",
        "Published_At": "2020-07-19T22:08:45Z",
        "Video_Title": "Gottesdienst  19.07.2020"
    },
    {
        "Channel_ID": "UCmer0iGUyA-G9aNAOeBPZDg",
        "Video_ID": "EdFdIq7-uUM",
        "View_Count": "117",
        "Published_At": "2020-07-12T22:16:16Z",
        "Video_Title": "Gottesdienst  12.07.2020"
    },
    {
        "Channel_ID": "UCmer0iGUyA-G9aNAOeBPZDg",
        "Video_ID": "dMsqgswEzfA",
        "View_Count": "96",
        "Published_At": "2020-07-12T11:13:18Z",
        "Video_Title": "Gottesdienst  12.07.2020"
    },
    {
        "Channel_ID": "UCmer0iGUyA-G9aNAOeBPZDg",
        "Video_ID": "9LztWn3gsvQ",
        "View_Count": "91",
        "Published_At": "2020-07-05T21:52:16Z",
        "Video_Title": "Gottesdienst  05.07.2020"
    },
    {
        "Channel_ID": "UCmer0iGUyA-G9aNAOeBPZDg",
        "Video_ID": "215L_ZkMog0",
        "View_Count": "132",
        "Published_At": "2020-06-28T22:16:04Z",
        "Video_Title": "Gottesdienst  28.06.2020"
    },
    {
        "Channel_ID": "UCmer0iGUyA-G9aNAOeBPZDg",
        "Video_ID": "KMwYDoZfeA4",
        "View_Count": "140",
        "Published_At": "2020-06-14T22:19:40Z",
        "Video_Title": "Gottesdienst  14.06.2020"
    },
    {
        "Channel_ID": "UCmer0iGUyA-G9aNAOeBPZDg",
        "Video_ID": "60vZs5yt95I",
        "View_Count": "176",
        "Published_At": "2020-06-07T21:58:58Z",
        "Video_Title": "Gottesdienst  07.06.2020"
    },
    {
        "Channel_ID": "UCmer0iGUyA-G9aNAOeBPZDg",
        "Video_ID": "MRJcX0-CQ_w",
        "View_Count": "228",
        "Published_At": "2020-05-31T22:09:33Z",
        "Video_Title": "Gottesdienst  31.05.2020"
    },
    {
        "Channel_ID": "UCmer0iGUyA-G9aNAOeBPZDg",
        "Video_ID": "UgL-VobIVlM",
        "View_Count": "183",
        "Published_At": "2020-05-24T18:00:11Z",
        "Video_Title": "Unsere Gottesdienste um 9 und 11 Uhr"
    },
    {
        "Channel_ID": "UCmer0iGUyA-G9aNAOeBPZDg",
        "Video_ID": "ilvKEZrimeU",
        "View_Count": "109",
        "Published_At": "2020-05-24T17:27:11Z",
        "Video_Title": "Gottesdienst  24.05.2020"
    },
    {
        "Channel_ID": "UCmer0iGUyA-G9aNAOeBPZDg",
        "Video_ID": "MXPYpUA4mCo",
        "View_Count": "137",
        "Published_At": "2020-05-17T16:59:26Z",
        "Video_Title": "Gottesdienst  17.05.2020"
    },
    {
        "Channel_ID": "UCmer0iGUyA-G9aNAOeBPZDg",
        "Video_ID": "cyFdv1FnTvQ",
        "View_Count": "411",
        "Published_At": "2020-05-15T13:31:38Z",
        "Video_Title": "Vision Gospelhouse"
    },
    {
        "Channel_ID": "UCmer0iGUyA-G9aNAOeBPZDg",
        "Video_ID": "cyFdv1FnTvQ",
        "View_Count": "411",
        "Published_At": "2020-05-15T13:31:38Z",
        "Video_Title": "Vision Gospelhouse"
    },
    {
        "Channel_ID": "UCmer0iGUyA-G9aNAOeBPZDg",
        "Video_ID": "v0bwkfTWUEg",
        "View_Count": "371",
        "Published_At": "2020-05-10T17:04:13Z",
        "Video_Title": "Gottesdienst  10.05.2020"
    },
    {
        "Channel_ID": "UCmer0iGUyA-G9aNAOeBPZDg",
        "Video_ID": "PKDZGV9s7cM",
        "View_Count": "251",
        "Published_At": "2020-05-07T14:00:14Z",
        "Video_Title": "J\u00fcngerschaftskurs - Die Taufe"
    },
    {
        "Channel_ID": "UCmer0iGUyA-G9aNAOeBPZDg",
        "Video_ID": "3Ifi_JHKQkI",
        "View_Count": "193",
        "Published_At": "2020-05-03T07:00:09Z",
        "Video_Title": "Gottesdienst"
    },
    {
        "Channel_ID": "UCmer0iGUyA-G9aNAOeBPZDg",
        "Video_ID": "wTJ3jYrVh_Q",
        "View_Count": "480",
        "Published_At": "2020-05-03T07:00:20Z",
        "Video_Title": "GOSPELHOUSE WORSHIP \u2013 Wohnzimmer Sessions (Teil 7)"
    },
    {
        "Channel_ID": "UCmer0iGUyA-G9aNAOeBPZDg",
        "Video_ID": "OornfofImPI",
        "View_Count": "184",
        "Published_At": "2020-04-30T14:00:09Z",
        "Video_Title": "JSK Teil3"
    },
    {
        "Channel_ID": "UCmer0iGUyA-G9aNAOeBPZDg",
        "Video_ID": "g4XLWGgrfvQ",
        "View_Count": "256",
        "Published_At": "2020-04-26T07:00:19Z",
        "Video_Title": "GOSPELHOUSE WORSHIP \u2013 Wohnzimmersessions (Teil 6)"
    },
    {
        "Channel_ID": "UCmer0iGUyA-G9aNAOeBPZDg",
        "Video_ID": "YgpXGOi4juQ",
        "View_Count": "357",
        "Published_At": "2020-04-26T07:00:08Z",
        "Video_Title": "WIE MACHE ICH DAS BESTE AUS MEINEM LEBEN ?"
    },
    {
        "Channel_ID": "UCmer0iGUyA-G9aNAOeBPZDg",
        "Video_ID": "wW6ojTUpBSc",
        "View_Count": "127",
        "Published_At": "2020-04-23T14:00:24Z",
        "Video_Title": "JSK Teil 2"
    },
    {
        "Channel_ID": "UCmer0iGUyA-G9aNAOeBPZDg",
        "Video_ID": "NVotp1-rAhQ",
        "View_Count": "347",
        "Published_At": "2020-04-19T07:00:12Z",
        "Video_Title": "Au\u00dferhalb der Norm"
    },
    {
        "Channel_ID": "UCmer0iGUyA-G9aNAOeBPZDg",
        "Video_ID": "j68MALHl9Ug",
        "View_Count": "145",
        "Published_At": "2020-04-19T07:00:28Z",
        "Video_Title": "GOSPELHOUSE WORSHIP \u2013 Wohnzimmersessions (Teil 5)"
    },
    {
        "Channel_ID": "UCmer0iGUyA-G9aNAOeBPZDg",
        "Video_ID": "tJBDRGdJtPs",
        "View_Count": "158",
        "Published_At": "2020-04-16T14:00:21Z",
        "Video_Title": "In der Nachfolge wachsen Teil 1"
    },
    {
        "Channel_ID": "UCmer0iGUyA-G9aNAOeBPZDg",
        "Video_ID": "njpBYVAD55w",
        "View_Count": "515",
        "Published_At": "2020-04-12T07:00:26Z",
        "Video_Title": "GOSPELHOUSE WORSHIP - Wohnzimmer Sessions (Teil 4) | Ostersonntag"
    },
    {
        "Channel_ID": "UCmer0iGUyA-G9aNAOeBPZDg",
        "Video_ID": "CcrLEdQLPw8",
        "View_Count": "420",
        "Published_At": "2020-04-12T07:00:07Z",
        "Video_Title": "Jesus ist... dein Gamechanger | Wohnzimmer Gottesdienst"
    },
    {
        "Channel_ID": "UCmer0iGUyA-G9aNAOeBPZDg",
        "Video_ID": "a2GZKwp7DS4",
        "View_Count": "724",
        "Published_At": "2020-04-10T08:00:01Z",
        "Video_Title": "GOSPELHOUSE WORSHIP - Wohnzimmer Sessions (Teil 3) | Karfreitag"
    },
    {
        "Channel_ID": "UCmer0iGUyA-G9aNAOeBPZDg",
        "Video_ID": "LAcB7Zlr_I0",
        "View_Count": "144",
        "Published_At": "2020-04-10T08:00:06Z",
        "Video_Title": "Wohnzimmer Abendmahl | Karfreitag"
    },
    {
        "Channel_ID": "UCmer0iGUyA-G9aNAOeBPZDg",
        "Video_ID": "gr6NWJeKRnk",
        "View_Count": "260",
        "Published_At": "2020-04-09T20:54:20Z",
        "Video_Title": "Wohnzimmer Gottesdienst Karfreitag | Unschlagbar in deiner Krise"
    },
    {
        "Channel_ID": "UCmer0iGUyA-G9aNAOeBPZDg",
        "Video_ID": "wCf5wSlCZLg",
        "View_Count": "978",
        "Published_At": "2020-04-05T05:00:11Z",
        "Video_Title": "GOSPELHOUSE WORSHIP - Wohnzimmer Sessions (Teil 2)"
    },
    {
        "Channel_ID": "UCmer0iGUyA-G9aNAOeBPZDg",
        "Video_ID": "EvY4Q-tpbaE",
        "View_Count": "407",
        "Published_At": "2020-04-04T23:49:59Z",
        "Video_Title": "Jesus ist \" Freund der S\u00fcnder\""
    },
    {
        "Channel_ID": "UCmer0iGUyA-G9aNAOeBPZDg",
        "Video_ID": "0-746XLd6Nw",
        "View_Count": "206",
        "Published_At": "2020-04-02T09:00:19Z",
        "Video_Title": "Wie kann ich von ganzem Herzen vergeben?"
    },
    {
        "Channel_ID": "UCmer0iGUyA-G9aNAOeBPZDg",
        "Video_ID": "5u2kCE7RiA4",
        "View_Count": "1608",
        "Published_At": "2020-03-29T07:00:02Z",
        "Video_Title": "GOSPELHOUSE WORSHIP - Wohnzimmer Sessions (Teil 1)"
    },
    {
        "Channel_ID": "UCmer0iGUyA-G9aNAOeBPZDg",
        "Video_ID": "Nbq5ulW0VOg",
        "View_Count": "450",
        "Published_At": "2020-03-29T07:00:05Z",
        "Video_Title": "\"H\u00f6hen und Tiefen\""
    },
    {
        "Channel_ID": "UCmer0iGUyA-G9aNAOeBPZDg",
        "Video_ID": "HBHLX7jauBI",
        "View_Count": "164",
        "Published_At": "2020-03-26T13:13:00Z",
        "Video_Title": "Wie gehe ich mit meinen Gef\u00fchlen um?"
    },
    {
        "Channel_ID": "UCmer0iGUyA-G9aNAOeBPZDg",
        "Video_ID": "txni00wQ570",
        "View_Count": "702",
        "Published_At": "2020-03-22T07:35:13Z",
        "Video_Title": "Gro\u00dfartige Dinge geschehen nicht in Komfortzonen"
    },
    {
        "Channel_ID": "UCmer0iGUyA-G9aNAOeBPZDg",
        "Video_ID": "CZjXO_U22s8",
        "View_Count": "263",
        "Published_At": "2020-03-19T20:52:53Z",
        "Video_Title": "Schluss mit alten Verhaltensmustern"
    },
    {
        "Channel_ID": "UCmer0iGUyA-G9aNAOeBPZDg",
        "Video_ID": "hLkxNORxJh4",
        "View_Count": "229",
        "Published_At": "2020-03-17T20:29:02Z",
        "Video_Title": "Der J\u00fcngerschaftskurs.  Einf\u00fchrung  up- in- out"
    }
]